Workbook

Sheet Légende
A1: Base de données Cuisine — addon WoW Forever
A3: Onglets
A4: Recettes : une ligne par recette (niveaux orange/jaune/vert/gris, appris chez un maître ou non).
A5: Composants : lien recette ↔ ingrédient avec la quantité (clé de jointure : id_recette, id_ingrédient).
A6: Ingrédients : liste unique des ingrédients, avec le nombre de recettes qui les utilisent (formule).
A7: Sources : où trouver chaque ingrédient (monstre, pêche, vendeur), une ligne par ingrédient et par zone. Rempli à partir de Wowhead Classic ; lignes jaunes libres pour compléter.
A8: Marchands : marchands de composants relevés en jeu par l'addon CuisineMarchands (PNJ, zone, mapID, position, composants).
A9: Marchands_recettes : recettes de cuisine vendues par des marchands (relevés en jeu), reliées aux recettes et au plan de quêtes.
A10: Rangs_métier : paliers d'apprentissage (Apprenti → Artisan).
A11: Sources_données : provenance et limites des données.
A13: Cellules à remplir
A14: Onglet Sources : les données viennent de Wowhead Classic (1.15.8), PAS de la bêta Forever. À confirmer en jeu : zones et niveaux peuvent différer.
... A32: Licence : QuestieDB (GPL v3, à confirmer) et AtlasLoot Classic (GPL v2) : publier l'addon avec ces données impose une licence compatible GPL, un fichier LICENSE et des crédits.

Sheet Recettes
A1: id_recette | B1: Type d'id | C1: Recette | D1: Nouveau dans Forever | E1: Appris chez un maître | F1: Qté produite | G1: Orange | H1: Jaune | I1: Vert | J1: Gris | K1: Brut (source) | L1: Contrôle | M1: Nb composants | N1: Orange (QuestieDB)
A2: 279981 | B2: sort | C2: Kit de feu de camp basique | D2: Oui | E2: Oui | F2: 1 | H2: 1 | I2: 3 | J2: 5 | K2: 135 | L2: OK | M2: =COUNTIF(Composants!A:A,A2) -> 1
A3: 249871 | B3: objet | C3: Frappé venimeux | D3: Oui | E3: Non | F3: 1 | K3: 2551015 | L3: À vérifier | M3: =COUNTIF(Composants!A:A,A3) -> 3
A4: 263509 | B4: objet | C4: Soufflé de Mur-Céleste | D4: Oui | E4: Non | F4: 1 | K4: 25203345 | L4: À vérifier | M4: =COUNTIF(Composants!A:A,A4) -> 2
A5: 818 | B5: sort | C5: Feu de camp basique | D5: Non | E5: Oui | F5: 1 | H5: 25 | I5: 50 | J5: 75 | K5: 255075 | L5: OK | M5: =COUNTIF(Composants!A:A,A5) -> 1 | N5: 25
A6: 249865 | B6: objet | C6: Thé de sérénité | D6: Oui | E6: Non | F6: 1 | G6: 25 | H6: 25 | I6: 45 | J6: 65 | K6: 25254565 | L6: OK | M6: =COUNTIF(Composants!A:A,A6) -> 2
A7: 263512 | B7: objet | C7: Bouchées à la chair de pinces | D7: Oui | E7: Non | F7: 1 | K7: 35304355 | L7: À vérifier | M7: =COUNTIF(Composants!A:A,A7) -> 2
A8: 250079 | B8: objet | C8: Délicieuses bouchées au raptor | D8: Oui | E8: Non | F8: 1 | G8: 25 | H8: 35 | I8: 55 | J8: 75 | K8: 25355575 | L8: OK | M8: =COUNTIF(Composants!A:A,A8) -> 2
A9: 6888 | B9: objet | C9: Oeufs aux herbes | D9: Non | E9: Oui | F9: 1 | H9: 45 | I9: 65 | J9: 85 | K9: 456585 | L9: OK | M9: =COUNTIF(Composants!A:A,A9) -> 2 | N9: 1
A10: 2679 | B10: objet | C10: Viande de loup grillée | D10: Non | E10: Oui | F10: 1 | H10: 45 | I10: 65 | J10: 85 | K10: 456585 | L10: OK | M10: =COUNTIF(Composants!A:A,A10) -> 1 | N10: 1
A11: 2681 | B11: objet | C11: Viande de sanglier rôtie | D11: Non | E11: Oui | F11: 1 | H11: 45 | I11: 65 | J11: 85 | K11: 456585 | L11: OK | M11: =COUNTIF(Composants!A:A,A11) -> 1 | N11: 1
A12: 12224 | B12: objet | C12: Aile de chauve-souris croustillante | D12: Non | E12: Non | F12: 1 | G12: 1 | H12: 45 | I12: 65 | J12: 85 | K12: 1456585 | L12: OK | M12: =COUNTIF(Composants!A:A,A12) -> 2 | N12: 1
A13: 17197 | B13: objet | C13: Biscuit de pain d'épice | D13: Non | E13: Non | F13: 1 | G13: 1 | H13: 45 | I13: 65 | J13: 85 | K13: 1456585 | L13: OK | M13: =COUNTIF(Composants!A:A,A13) -> 2 | N13: 1
A14: 6290 | B14: objet | C14: Goujon brillant | D14: Non | E14: Non | F14: 1 | G14: 1 | H14: 45 | I14: 65 | J14: 85 | K14: 1456585 | L14: OK | M14: =COUNTIF(Composants!A:A,A14) -> 1 | N14: 1
A15: 787 | B15: objet | C15: Maquereau ombré | D15: Non | E15: Non | F15: 1 | G15: 1 | H15: 45 | I15: 65 | J15: 85 | K15: 1456585 | L15: OK | M15: =COUNTIF(Composants!A:A,A15) -> 1 | N15: 1
A16: 2680 | B16: objet | C16: Viande de loup épicée | D16: Non | E16: Oui | F16: 1 | H16: 50 | I16: 70 | J16: 90 | K16: 507090 | L16: OK | M16: =COUNTIF(Composants!A:A,A16) -> 2 | N16: 30
A17: 5472 | B17: objet | C17: Kébab d'araignée kaldorei | D17: Non | E17: Non | F17: 1 | G17: 10 | H17: 50 | I17: 70 | J17: 90 | K17: 10507090 | L17: OK | M17: =COUNTIF(Composants!A:A,A17) -> 1 | N17: 10
A18: 5473 | B18: objet | C18: Surprise du scorpide | D18: Non | E18: Non | F18: 1 | G18: 20 | H18: 60 | I18: 80 | J18: 100 | K18: 206080100 | L18: OK | M18: =COUNTIF(Composants!A:A,A18) -> 1 | N18: 20
A19: 2888 | B19: objet | C19: Côtes de sanglier à la bière | D19: Non | E19: Non | F19: 1 | G19: 25 | H19: 60 | I19: 80 | J19: 100 | K19: 256080100 | L19: OK | M19: =COUNTIF(Composants!A:A,A19) -> 2 | N19: 25
A20: 17198 | B20: objet | C20: Lait de poule | D20: Non | E20: Non | F20: 1 | G20: 35 | H20: 75 | I20: 95 | J20: 115 | K20: 357595115 | L20: OK | M20: =COUNTIF(Composants!A:A,A20) -> 4 | N20: 35
A21: 5474 | B21: objet | C21: Viande de kodo rôtie | D21: Non | E21: Non | F21: 2 | G21: 35 | H21: 75 | I21: 95 | J21: 115 | K21: 357595115 | L21: OK | M21: =COUNTIF(Composants!A:A,A21) -> 2 | N21: 35
A22: 250080 | B22: objet | C22: Omelette de petit déjeuner | D22: Oui | E22: Non | F22: 1 | G22: 75 | H22: 75 | I22: 93 | J22: 110 | K22: 757593110 | L22: OK | M22: =COUNTIF(Composants!A:A,A22) -> 2
A23: 6890 | B23: objet | C23: Viande d'ours fumée | D23: Non | E23: Non | F23: 1 | G23: 40 | H23: 80 | I23: 100 | J23: 120 | K23: 4080100120 | L23: OK | M23: =COUNTIF(Composants!A:A,A23) -> 1 | N23: 40
A24: 249872 | B24: objet | C24: Frappé gélatineux | D24: Oui | E24: Non | F24: 1 | K24: 100859095 | L24: À vérifier | M24: =COUNTIF(Composants!A:A,A24) -> 3
A25: 249866 | B25: objet | C25: Thé royal | D25: Oui | E25: Non | F25: 1 | K25: 10085105125 | L25: À vérifier | M25: =COUNTIF(Composants!A:A,A25) -> 2
A26: 5525 | B26: objet | C26: Palourdes bouillies | D26: Non | E26: Oui | F26: 1 | H26: 90 | I26: 110 | J26: 130 | K26: 90110130 | L26: OK | M26: =COUNTIF(Composants!A:A,A26) -> 2 | N26: 50
A27: 2684 | B27: objet | C27: Steak de coyote | D27: Non | E27: Oui | F27: 1 | H27: 90 | I27: 110 | J27: 130 | K27: 90110130 | L27: OK | M27: =COUNTIF(Composants!A:A,A27) -> 1 | N27: 65
A28: 5477 | B28: objet | C28: Brouet de trotteur | D28: Non | E28: Non | F28: 2 | G28: 50 | H28: 90 | I28: 110 | J28: 130 | K28: 5090110130 | L28: OK | M28: =COUNTIF(Composants!A:A,A28) -> 2 | N28: 50
A29: 6316 | B29: objet | C29: Délice de furie du loch | D29: Non | E29: Non | F29: 1 | G29: 50 | H29: 90 | I29: 110 | J29: 130 | K29: 5090110130 | L29: OK | M29: =COUNTIF(Composants!A:A,A29) -> 2 | N29: 50
A30: 5476 | B30: objet | C30: Filet de furie | D30: Non | E30: Non | F30: 2 | G30: 50 | H30: 90 | I30: 110 | J30: 130 | K30: 5090110130 | L30: OK | M30: =COUNTIF(Composants!A:A,A30) -> 2 | N30: 50
A31: 4592 | B31: objet | C31: Lutjan à longue mâchoire | D31: Non | E31: Non | F31: 1 | G31: 50 | H31: 90 | I31: 110 | J31: 130 | K31: 5090110130 | L31: OK | M31: =COUNTIF(Composants!A:A,A31) -> 1 | N31: 50
A32: 5095 | B32: objet | C32: Thon arc-en-ciel | D32: Non | E32: Non | F32: 1 | G32: 50 | H32: 90 | I32: 110 | J32: 130 | K32: 5090110130 | L32: OK | M32: =COUNTIF(Composants!A:A,A32) -> 1 | N32: 50
A33: 724 | B33: objet | C33: Tourte au foie de Broche-tripes | D33: Non | E33: Non | F33: 1 | G33: 50 | H33: 90 | I33: 110 | J33: 130 | K33: 5090110130 | L33: OK | M33: =COUNTIF(Composants!A:A,A33) -> 2 | N33: 50
A34: 279961 | B34: objet | C34: Kit de feu de camp de compagnon | D34: Oui | E34: Non | F34: 1 | G34: 90 | H34: 90 | I34: 115 | J34: 140 | K34: 9090115140 | L34: OK | M34: =COUNTIF(Composants!A:A,A34) -> 1
A35: 3220 | B35: objet | C35: Boudin | D35: Non | E35: Non | F35: 2 | G35: 60 | H35: 100 | I35: 120 | J35: 140 | K35: 60100120140 | L35: OK | M35: =COUNTIF(Composants!A:A,A35) -> 3 | N35: 60
A36: 7676 | B36: objet | C36: Thé de chardon | D36: Non | E36: Non | F36: 1 | G36: 60 | H36: 100 | I36: 120 | J36: 140 | K36: 60100120140 | L36: OK | M36: =COUNTIF(Composants!A:A,A36) -> 2 | N36: 60
A37: 2683 | B37: objet | C37: Beignet de crabe | D37: Non | E37: Oui | F37: 1 | H37: 115 | I37: 135 | J37: 155 | K37: 115135155 | L37: OK | M37: =COUNTIF(Composants!A:A,A37) -> 2 | N37: 75
A38: 250077 | B38: objet | C38: Émincé de raptor aux deux épices | D38: Oui | E38: Non | F38: 1 | G38: 75 | H38: 115 | I38: 133 | J38: 150 | K38: 75115133150 | L38: OK | M38: =COUNTIF(Composants!A:A,A38) -> 2
A39: 733 | B39: objet | C39: Ragoût de la marche de l'Ouest | D39: Non | E39: Non | F39: 1 | G39: 75 | H39: 115 | I39: 135 | J39: 155 | K39: 75115135155 | L39: OK | M39: =COUNTIF(Composants!A:A,A39) -> 3 | N39: 75
A40: 2687 | B40: objet | C40: Côtes de porc séchées | D40: Non | E40: Oui | F40: 1 | H40: 120 | I40: 140 | J40: 160 | K40: 120140160 | L40: OK | M40: =COUNTIF(Composants!A:A,A40) -> 2 | N40: 110
A41: 21072 | B41: objet | C41: Sagerelle fumée | D41: Non | E41: Non | F41: 1 | G41: 80 | H41: 120 | I41: 140 | J41: 160 | K41: 80120140160 | L41: OK | M41: =COUNTIF(Composants!A:A,A41) -> 2 | N41: 80
A42: 3662 | B42: objet | C42: Steak de crocilisque | D42: Non | E42: Non | F42: 1 | G42: 80 | H42: 120 | I42: 140 | J42: 160 | K42: 80120140160 | L42: OK | M42: =COUNTIF(Composants!A:A,A42) -> 2 | N42: 80
A43: 6657 | B43: objet | C43: Délice de déviant | D43: Non | E43: Non | F43: 1 | G43: 85 | H43: 125 | I43: 145 | J43: 165 | K43: 85125145165 | L43: OK | M43: =COUNTIF(Composants!A:A,A43) -> 2 | N43: 85
A44: 251525 | B44: objet | C44: Délice de fantaileron | D44: Oui | E44: Non | F44: 1 | G44: 85 | H44: 125 | I44: 145 | J44: 165 | K44: 85125145165 | L44: OK | M44: =COUNTIF(Composants!A:A,A44) -> 2
A45: 2682 | B45: objet | C45: Pince de crabe farcie | D45: Non | E45: Non | F45: 1 | G45: 85 | H45: 125 | I45: 145 | J45: 165 | K45: 85125145165 | L45: OK | M45: =COUNTIF(Composants!A:A,A45) -> 2 | N45: 85
A46: 5478 | B46: objet | C46: Brouet de rat | D46: Non | E46: Non | F46: 2 | G46: 90 | H46: 130 | I46: 150 | J46: 170 | K46: 90130150170 | L46: OK | M46: =COUNTIF(Composants!A:A,A46) -> 1 | N46: 90
A47: 3663 | B47: objet | C47: Soupe aux ailerons de murloc | D47: Non | E47: Non | F47: 1 | G47: 90 | H47: 130 | I47: 150 | J47: 170 | K47: 90130150170 | L47: OK | M47: =COUNTIF(Composants!A:A,A47) -> 2 | N47: 90
A48: 5526 | B48: objet | C48: Soupe de palourdes | D48: Non | E48: Non | F48: 1 | G48: 90 | H48: 130 | I48: 150 | J48: 170 | K48: 90130150170 | L48: OK | M48: =COUNTIF(Composants!A:A,A48) -> 3 | N48: 90
A49: 2685 | B49: objet | C49: Côtes de porc aux herbes | D49: Non | E49: Non | F49: 1 | G49: 110 | H49: 130 | I49: 150 | J49: 170 | K49: 110130150170 | L49: OK | M49: =COUNTIF(Composants!A:A,A49) -> 2 | N49: 110
A50: 1082 | B50: objet | C50: Goulash des Carmines | D50: Non | E50: Non | F50: 1 | G50: 100 | H50: 135 | I50: 155 | J50: 175 | K50: 100135155175 | L50: OK | M50: =COUNTIF(Composants!A:A,A50) -> 2 | N50: 100
A51: 249873 | B51: objet | C51: Frppl mrrggl | D51: Oui | E51: Non | F51: 1 | G51: 125 | H51: 135 | I51: 140 | J51: 145 | K51: 125135140145 | L51: OK | M51: =COUNTIF(Composants!A:A,A51) -> 3
A52: 1017 | B52: objet | C52: Kébab de loup assaisonné | D52: Non | E52: Non | F52: 3 | G52: 100 | H52: 140 | I52: 160 | J52: 180 | K52: 100140160180 | L52: OK | M52: =COUNTIF(Composants!A:A,A52) -> 2 | N52: 100
A53: 4593 | B53: objet | C53: Poisson-chat moustachu | D53: Non | E53: Non | F53: 1 | G53: 100 | H53: 140 | I53: 160 | J53: 180 | K53: 100140160180 | L53: OK | M53: =COUNTIF(Composants!A:A,A53) -> 1 | N53: 100
A54: 5479 | B54: objet | C54: Queue de lézard croquante | D54: Non | E54: Non | F54: 2 | G54: 100 | H54: 140 | I54: 160 | J54: 180 | K54: 100140160180 | L54: OK | M54: =COUNTIF(Composants!A:A,A54) -> 2 | N54: 100
A55: 279957 | B55: objet | C55: Festin de Macaron | D55: Oui | E55: Non | F55: 1 | G55: 140 | H55: 140 | I55: 143 | J55: 145 | K55: 140140143145 | L55: OK | M55: =COUNTIF(Composants!A:A,A55) -> 3
A56: 3726 | B56: objet | C56: Steak de grand ours | D56: Non | E56: Non | F56: 1 | G56: 110 | H56: 150 | I56: 170 | J56: 190 | K56: 110150170190 | L56: OK | M56: =COUNTIF(Composants!A:A,A56) -> 2 | N56: 110
A57: 3666 | B57: objet | C57: Tourte d'araignée fondante | D57: Non | E57: Non | F57: 1 | G57: 110 | H57: 150 | I57: 170 | J57: 190 | K57: 110150170190 | L57: OK | M57: =COUNTIF(Composants!A:A,A57) -> 2 | N57: 110
A58: 5480 | B58: objet | C58: Venaison dégraissée | D58: Non | E58: Non | F58: 2 | G58: 110 | H58: 150 | I58: 170 | J58: 190 | K58: 110150170190 | L58: OK | M58: =COUNTIF(Composants!A:A,A58) -> 2 | N58: 110
A59: 249867 | B59: objet | C59: Thé aux racines | D59: Oui | E59: Non | F59: 1 | G59: 125 | H59: 155 | I59: 170 | J59: 185 | K59: 125155170185 | L59: OK | M59: =COUNTIF(Composants!A:A,A59) -> 2
A60: 3664 | B60: objet | C60: Gombo de crocilisque | D60: Non | E60: Non | F60: 1 | G60: 120 | H60: 160 | I60: 180 | J60: 200 | K60: 120160180200 | L60: OK | M60: =COUNTIF(Composants!A:A,A60) -> 2 | N60: 120
A61: 20074 | B61: objet | C61: Ragoût épais de crocilisque | D61: Non | E61: Non | F61: 1 | G61: 150 | H61: 160 | I61: 180 | J61: 200 | K61: 150160180200 | L61: OK | M61: =COUNTIF(Composants!A:A,A61) -> 2 | N61: 150
A62: 5527 | B62: objet | C62: Palourdes gobelines | D62: Non | E62: Oui | F62: 1 | H62: 165 | I62: 185 | J62: 205 | K62: 165185205 | L62: OK | M62: =COUNTIF(Composants!A:A,A62) -> 2 | N62: 125
A63: 12209 | B63: objet | C63: Steak de loup | D63: Non | E63: Non | F63: 1 | G63: 125 | H63: 165 | I63: 185 | J63: 205 | K63: 125165185205 | L63: OK | M63: =COUNTIF(Composants!A:A,A63) -> 2 | N63: 125
A64: 3665 | B64: objet | C64: Omelette au goût étrange | D64: Non | E64: Non | F64: 1 | G64: 130 | H64: 170 | I64: 190 | J64: 210 | K64: 130170190210 | L64: OK | M64: =COUNTIF(Composants!A:A,A64) -> 2 | N64: 130
A65: 3727 | B65: objet | C65: Côtelettes de lion épicées | D65: Non | E65: Non | F65: 1 | G65: 125 | H65: 175 | I65: 195 | J65: 215 | K65: 125175195215 | L65: OK | M65: =COUNTIF(Composants!A:A,A65) -> 2 | N65: 125
A66: 250072 | B66: objet | C66: Steak de frappe rapide | D66: Oui | E66: Non | F66: 1 | K66: 275175190205 | L66: À vérifier | M66: =COUNTIF(Composants!A:A,A66) -> 2
A67: 249874 | B67: objet | C67: Frappé calcifié | D67: Oui | E67: Non | F67: 1 | G67: 180 | H67: 185 | I67: 190 | J67: 195 | K67: 180185190195 | L67: OK | M67: =COUNTIF(Composants!A:A,A67) -> 3
A68: 250073 | B68: objet | C68: Côtelettes de raptor bouillantes | D68: Oui | E68: Non | F68: 1 | K68: 275185200215 | L68: À vérifier | M68: =COUNTIF(Composants!A:A,A68) -> 2
A69: 3728 | B69: objet | C69: Délicieux steak de lion | D69: Non | E69: Non | F69: 1 | G69: 150 | H69: 190 | I69: 210 | J69: 230 | K69: 150190210230 | L69: OK | M69: =COUNTIF(Composants!A:A,A69) -> 2 | N69: 150
A70: 4594 | B70: objet | C70: Morue rochécaille | D70: Non | E70: Non | F70: 1 | G70: 175 | H70: 190 | I70: 210 | J70: 230 | K70: 175190210230 | L70: OK | M70: =COUNTIF(Composants!A:A,A70) -> 1 | N70: 175
A71: 250078 | B71: objet | C71: Oeufs brouillés géants | D71: Oui | E71: Non | F71: 1 | G71: 175 | H71: 195 | I71: 208 | J71: 220 | K71: 175195208220 | L71: OK | M71: =COUNTIF(Composants!A:A,A71) -> 2
A72: 249868 | B72: objet | C72: Thé de triage | D72: Oui | E72: Non | F72: 1 | G72: 180 | H72: 195 | I72: 215 | J72: 235 | K72: 180195215235 | L72: OK | M72: =COUNTIF(Composants!A:A,A72) -> 2
A73: 250074 | B73: objet | C73: Poitrine d'ours | D73: Oui | E73: Non | F73: 1 | G73: 175 | H73: 200 | I73: 210 | J73: 220 | K73: 175200210220 | L73: OK | M73: =COUNTIF(Composants!A:A,A73) -> 2
A74: 274976 | B74: objet | C74: Bonne vieille viande de brochepâle | D74: Oui | E74: Non | F74: 1 | G74: 185 | H74: 200 | I74: 215 | J74: 230 | K74: 185200215230 | L74: OK | M74: =COUNTIF(Composants!A:A,A74) -> 2
A75: 279974 | B75: objet | C75: Kit de feu de camp de spécialiste | D75: Oui | E75: Non | F75: 1 | G75: 200 | H75: 200 | I75: 213 | J75: 225 | K75: 200200213225 | L75: OK | M75: =COUNTIF(Composants!A:A,A75) -> 1
A76: 250081 | B76: objet | C76: Linguines aux palourdes | D76: Oui | E76: Non | F76: 1 | K76: 275200220240 | L76: À vérifier | M76: =COUNTIF(Composants!A:A,A76) -> 2
A77: 8957 | B77: objet | C77: Flétan épineux | D77: Oui | E77: Oui | F77: 1 | H77: 210 | I77: 215 | J77: 220 | K77: 210215220 | L77: OK | M77: =COUNTIF(Composants!A:A,A77) -> 1
A78: 10841 | B78: objet | C78: Thé de dorépine | D78: Non | E78: Oui | F78: 4 | H78: 215 | I78: 235 | J78: 255 | K78: 215235255 | L78: OK | M78: =COUNTIF(Composants!A:A,A78) -> 2 | N78: 175
A79: 4457 | B79: objet | C79: Aile de busard grillée | D79: Non | E79: Non | F79: 1 | G79: 175 | H79: 215 | I79: 235 | J79: 255 | K79: 175215235255 | L79: OK | M79: =COUNTIF(Composants!A:A,A79) -> 2 | N79: 175
A80: 6038 | B80: objet | C80: Ardeur de palourde géante | D80: Non | E80: Non | F80: 1 | G80: 175 | H80: 215 | I80: 235 | J80: 255 | K80: 175215235255 | L80: OK | M80: =COUNTIF(Composants!A:A,A80) -> 2 | N80: 175
A81: 3729 | B81: objet | C81: Bisque de tortue apaisante | D81: Non | E81: Non | F81: 1 | G81: 175 | H81: 215 | I81: 235 | J81: 255 | K81: 175215235255 | L81: OK | M81: =COUNTIF(Composants!A:A,A81) -> 2 | N81: 175
A82: 13851 | B82: objet | C82: Côtes de loup épicées | D82: Non | E82: Non | F82: 1 | G82: 175 | H82: 215 | I82: 235 | J82: 255 | K82: 175215235255 | L82: OK | M82: =COUNTIF(Composants!A:A,A82) -> 2 | N82: 175
A83: 21217 | B83: objet | C83: Délice de sagerelle | D83: Non | E83: Non | F83: 1 | G83: 175 | H83: 215 | I83: 235 | J83: 255 | K83: 175215235255 | L83: OK | M83: =COUNTIF(Composants!A:A,A83) -> 2 | N83: 175
A84: 12212 | B84: objet | C84: Ragoût de la jungle | D84: Non | E84: Non | F84: 2 | G84: 175 | H84: 215 | I84: 235 | J84: 255 | K84: 175215235255 | L84: OK | M84: =COUNTIF(Composants!A:A,A84) -> 3 | N84: 175
A85: 12214 | B85: objet | C85: Ragoût mystère | D85: Non | E85: Non | F85: 1 | G85: 175 | H85: 215 | I85: 235 | J85: 255 | K85: 175215235255 | L85: OK | M85: =COUNTIF(Composants!A:A,A85) -> 2 | N85: 175
A86: 12210 | B86: objet | C86: Rôti de raptor | D86: Non | E86: Non | F86: 1 | G86: 175 | H86: 215 | I86: 235 | J86: 255 | K86: 175215235255 | L86: OK | M86: =COUNTIF(Composants!A:A,A86) -> 2 | N86: 175
A87: 12213 | B87: objet | C87: Tourte surprise | D87: Non | E87: Non | F87: 1 | G87: 175 | H87: 215 | I87: 235 | J87: 255 | K87: 175215235255 | L87: OK | M87: =COUNTIF(Composants!A:A,A87) -> 2 | N87: 175
A88: 8364 | B88: objet | C88: Truite tête-mithril | D88: Non | E88: Non | F88: 1 | G88: 175 | H88: 215 | I88: 235 | J88: 255 | K88: 175215235255 | L88: OK | M88: =COUNTIF(Composants!A:A,A88) -> 1 | N88: 175
A89: 249875 | B89: objet | C89: Frappé épicé | D89: Oui | E89: Non | F89: 1 | G89: 200 | H89: 215 | I89: 220 | J89: 225 | K89: 200215220225 | L89: OK | M89: =COUNTIF(Composants!A:A,A89) -> 3
A90: 274971 | B90: objet | C90: Ragoût de fruits de mer saumâtre | D90: Oui | E90: Non | F90: 1 | G90: 200 | H90: 220 | I90: 230 | J90: 240 | K90: 200220230240 | L90: OK | M90: =COUNTIF(Composants!A:A,A90) -> 3
A91: 249869 | B91: objet | C91: Thé du soleil | D91: Oui | E91: Non | F91: 1 | G91: 200 | H91: 220 | I91: 235 | J91: 250 | K91: 200220235250 | L91: OK | M91: =COUNTIF(Composants!A:A,A91) -> 2
A92: 250065 | B92: objet | C92: Mini-burgers de cerf savoureux | D92: Oui | E92: Non | F92: 1 | G92: 225 | H92: 225 | I92: 240 | J92: 255 | K92: 225225240255 | L92: OK | M92: =COUNTIF(Composants!A:A,A92) -> 2
A93: 250076 | B93: objet | C93: Paupiette de raptor | D93: Oui | E93: Non | F93: 1 | G93: 225 | H93: 225 | I93: 238 | J93: 250 | K93: 225225238250 | L93: OK | M93: =COUNTIF(Composants!A:A,A93) -> 2
A94: 17222 | B94: objet | C94: Saucisse d'araignée | D94: Non | E94: Oui | F94: 1 | H94: 240 | I94: 260 | J94: 280 | K94: 240260280 | L94: OK | M94: =COUNTIF(Composants!A:A,A94) -> 1 | N94: 200
A95: 12217 | B95: objet | C95: Chili de souffle de dragon | D95: Non | E95: Non | F95: 1 | G95: 200 | H95: 240 | I95: 260 | J95: 280 | K95: 200240260280 | L95: OK | M95: =COUNTIF(Composants!A:A,A95) -> 3 | N95: 200
A96: 12215 | B96: objet | C96: Ragoût épais de kodo | D96: Non | E96: Non | F96: 2 | G96: 200 | H96: 240 | I96: 260 | J96: 280 | K96: 200240260280 | L96: OK | M96: =COUNTIF(Composants!A:A,A96) -> 3 | N96: 200
A97: 249876 | B97: objet | C97: Frappé pernicieux | D97: Oui | E97: Non | F97: 1 | K97: 250240245250 | L97: À vérifier | M97: =COUNTIF(Composants!A:A,A97) -> 3
A98: 286152 | B98: objet | C98: Poisson cuirassé | D98: Oui | E98: Non | F98: 1 | G98: 225 | H98: 245 | I98: 250 | J98: 255 | K98: 225245250255 | L98: OK | M98: =COUNTIF(Composants!A:A,A98) -> 2
A99: 238638 | B99: objet | C99: Filet de flanc | D99: Non | E99: Non | F99: 2 | G99: 250 | H99: 260 | I99: 270 | J99: 280 | K99: 250260270280 | L99: OK | M99: =COUNTIF(Composants!A:A,A99) -> 2
A100: 238639 | B100: objet | C100: Omelette du Lever de soleil | D100: Non | E100: Non | F100: 2 | G100: 250 | H100: 260 | I100: 270 | J100: 280 | K100: 250260270280 | L100: OK | M100: =COUNTIF(Composants!A:A,A100) -> 2
...

Sheet Plan_quêtes
A1: Quête n° | B1: Rang requis | C1: Compétence début | D1: Compétence fin | E1: Recette | F1: id_recette | G1: Couleur | H1: Chance par craft | I1: Nb de crafts | J1: Obtention de la recette | K1: Intitulé de quête | L1: Ingrédients sans source | M1: Détail d'obtention (QuestieDB / web)
A2: 1 | B2: =INDEX(Rangs_métier!$A$2:$A$5,MATCH(C2,Rangs_métier!$B$2:$B$5,1)) -> Apprenti | C2: 1 | D2: 45 | E2: Aile de chauve-souris croustillante | F2: 12224 | G2: Orange | H2: =INDEX(Hypothèses!$B$4:$B$6,MATCH(G2,Hypothèses!$A$4:$A$6,0)) -> 1 | I2: =ROUNDUP((D2-C2)/H2,0) -> 44 | J2: =IF(INDEX(Recettes!$E:$E,MATCH(F2,Recettes!$A:$A,0))="Oui","Maître",IFERROR("Marchand : "&INDEX(Marchands_recettes!$B:$B,MATCH(F2,Marchands_recettes!$I:$I,0)),"Autre (vendeur / quête / butin)")) -> Marchand : Abigail Shiel | K2: ="Cuisiner "&I2&"× "&E2&" (compétence "&C2&" → "&D2&")" -> Cuisiner 44× Aile de chauve-souris croustillante (compétence 1 → 45) | L2: =COUNTIFS(Plan_matériaux!$A:$A,A2,Plan_matériaux!$J:$J,"À renseigner") -> 0 | M2: Abigail Shiel (Clairières de Tirisfal, 61 / 52,4) - relevé en jeu.
A3: 2 | B3: =INDEX(Rangs_métier!$A$2:$A$5,MATCH(C3,Rangs_métier!$B$2:$B$5,1)) -> Apprenti | C3: 45 | D3: 80 | E3: Viande d'ours fumée | F3: 6890 | G3: Orange | H3: =INDEX(Hypothèses!$B$4:$B$6,MATCH(G3,Hypothèses!$A$4:$A$6,0)) -> 1 | I3: =ROUNDUP((D3-C3)/H3,0) -> 35 | J3: =IF(INDEX(Recettes!$E:$E,MATCH(F3,Recettes!$A:$A,0))="Oui","Maître",IFERROR("Marchand : "&INDEX(Marchands_recettes!$B:$B,MATCH(F3,Marchands_recettes!$I:$I,0)),"Autre (vendeur / quête / butin)")) -> Marchand : Andrew Hilbert | K3: ="Cuisiner "&I3&"× "&E3&" (compétence "&C3&" → "&D3&")" -> Cuisiner 35× Viande d'ours fumée (compétence 45 → 80) | L3: =COUNTIFS(Plan_matériaux!$A:$A,A3,Plan_matériaux!$J:$J,"À renseigner") -> 0 | M3: Andrew Hilbert (Forêt des Pins argentés, 43,2 / 40,7) - Recette : Viande d'ours fumée, compétence 40 - QuestieDB, à confirmer en jeu.
A4: 3 | B4: =INDEX(Rangs_métier!$A$2:$A$5,MATCH(C4,Rangs_métier!$B$2:$B$5,1)) -> Compagnon | C4: 80 | D4: 120 | E4: Côtes de porc séchées | F4: 2687 | G4: Orange | H4: =INDEX(Hypothèses!$B$4:$B$6,MATCH(G4,Hypothèses!$A$4:$A$6,0)) -> 1 | I4: =ROUNDUP((D4-C4)/H4,0) -> 40 | J4: =IF(INDEX(Recettes!$E:$E,MATCH(F4,Recettes!$A:$A,0))="Oui","Maître",IFERROR("Marchand : "&INDEX(Marchands_recettes!$B:$B,MATCH(F4,Marchands_recettes!$I:$I,0)),"Autre (vendeur / quête / butin)")) -> Maître | K4: ="Cuisiner "&I4&"× "&E4&" (compétence "&C4&" → "&D4&")" -> Cuisiner 40× Côtes de porc séchées (compétence 80 → 120) | L4: =COUNTIFS(Plan_matériaux!$A:$A,A4,Plan_matériaux!$J:$J,"À renseigner") -> 0 | M4: Maître de cuisine, Horde : Zamja (Orgrimmar 57,4 / 54), Eunice Burch (Fossoyeuse 62,1 / 44,9), Aska Mistrunner (Pitons-du-Tonnerre 50,7 / 53,1). Niveau orange : 110 (QuestieDB) contre 80 (hypothèse) - à vérifier en jeu.
A5: 4 | B5: =INDEX(Rangs_métier!$A$2:$A$5,MATCH(C5,Rangs_métier!$B$2:$B$5,1)) -> Compagnon | C5: 120 | D5: 160 | E5: Gombo de crocilisque | F5: 3664 | G5: Orange | H5: =INDEX(Hypothèses!$B$4:$B$6,MATCH(G5,Hypothèses!$A$4:$A$6,0)) -> 1 | I5: =ROUNDUP((D5-C5)/H5,0) -> 40 | J5: =IF(INDEX(Recettes!$E:$E,MATCH(F5,Recettes!$A:$A,0))="Oui","Maître",IFERROR("Marchand : "&INDEX(Marchands_recettes!$B:$B,MATCH(F5,Marchands_recettes!$I:$I,0)),"Autre (vendeur / quête / butin)")) -> Autre (vendeur / quête / butin) | K5: ="Cuisiner "&I5&"× "&E5&" (compétence "&C5&" → "&D5&")" -> Cuisiner 40× Gombo de crocilisque (compétence 120 → 160) | L5: =COUNTIFS(Plan_matériaux!$A:$A,A5,Plan_matériaux!$J:$J,"À renseigner") -> 0 | M5: Aucune source Horde connue dans QuestieDB (vendeur Kendor Kabonka à Hurlevent et quête 471 : Alliance). Piste Horde : Côtelettes de lion épicées (Zargh, Les Tarides 52,6 / 29,8, compétence 125) - à évaluer.
A6: 5 | B6: =INDEX(Rangs_métier!$A$2:$A$5,MATCH(C6,Rangs_métier!$B$2:$B$5,1)) -> Expert | C6: 160 | D6: 190 | E6: Délicieux steak de lion | F6: 3728 | G6: Orange | H6: =INDEX(Hypothèses!$B$4:$B$6,MATCH(G6,Hypothèses!$A$4:$A$6,0)) -> 1 | I6: =ROUNDUP((D6-C6)/H6,0) -> 30 | J6: =IF(INDEX(Recettes!$E:$E,MATCH(F6,Recettes!$A:$A,0))="Oui","Maître",IFERROR("Marchand : "&INDEX(Marchands_recettes!$B:$B,MATCH(F6,Marchands_recettes!$I:$I,0)),"Autre (vendeur / quête / butin)")) -> Autre (vendeur / quête / butin) | K6: ="Cuisiner "&I6&"× "&E6&" (compétence "&C6&" → "&D6&")" -> Cuisiner 30× Délicieux steak de lion (compétence 160 → 190) | L6: =COUNTIFS(Plan_matériaux!$A:$A,A6,Plan_matériaux!$J:$J,"À renseigner") -> 0 | M6: Aucune source Horde connue dans QuestieDB (récompense de la quête 564 « Un problème très coûteux », Alliance). Piste Horde : Côtelettes de lion épicées (Zargh, Les Tarides) - à évaluer.
A7: 6 | B7: =INDEX(Rangs_métier!$A$2:$A$5,MATCH(C7,Rangs_métier!$B$2:$B$5,1)) -> Expert | C7: 190 | D7: 200 | E7: Bonne vieille viande de brochepâle | F7: 274976 | G7: Orange | H7: =INDEX(Hypothèses!$B$4:$B$6,MATCH(G7,Hypothèses!$A$4:$A$6,0)) -> 1 | I7: =ROUNDUP((D7-C7)/H7,0) -> 10 | J7: =IF(INDEX(Recettes!$E:$E,MATCH(F7,Recettes!$A:$A,0))="Oui","Maître",IFERROR("Marchand : "&INDEX(Marchands_recettes!$B:$B,MATCH(F7,Marchands_recettes!$I:$I,0)),"Autre (vendeur / quête / butin)")) -> Autre (vendeur / quête / butin) | K7: ="Cuisiner "&I7&"× "&E7&" (compétence "&C7&" → "&D7&")" -> Cuisiner 10× Bonne vieille viande de brochepâle (compétence 190 → 200) | L7: =COUNTIFS(Plan_matériaux!$A:$A,A7,Plan_matériaux!$J:$J,"À renseigner") -> 0 | M7: Recette propre à Forever : source inconnue.
A8: 7 | B8: =INDEX(Rangs_métier!$A$2:$A$5,MATCH(C8,Rangs_métier!$B$2:$B$5,1)) -> Expert | C8: 200 | D8: 240 | E8: Saucisse d'araignée | F8: 17222 | G8: Orange | H8: =INDEX(Hypothèses!$B$4:$B$6,MATCH(G8,Hypothèses!$A$4:$A$6,0)) -> 1 | I8: =ROUNDUP((D8-C8)/H8,0) -> 40 | J8: =IF(INDEX(Recettes!$E:$E,MATCH(F8,Recettes!$A:$A,0))="Oui","Maître",IFERROR("Marchand : "&INDEX(Marchands_recettes!$B:$B,MATCH(F8,Marchands_recettes!$I:$I,0)),"Autre (vendeur / quête / butin)")) -> Maître | K8: ="Cuisiner "&I8&"× "&E8&" (compétence "&C8&" → "&D8&")" -> Cuisiner 40× Saucisse d'araignée (compétence 200 → 240) | L8: =COUNTIFS(Plan_matériaux!$A:$A,A8,Plan_matériaux!$J:$J,"À renseigner") -> 0 | M8: Maître de cuisine (voir quête 3 pour les maîtres Horde). Niveau orange 200 (QuestieDB).
A9: 8 | B9: =INDEX(Rangs_métier!$A$2:$A$5,MATCH(C9,Rangs_métier!$B$2:$B$5,1)) -> Artisan | C9: 240 | D9: 265 | E9: Barracuda luisant cuit | F9: 13927 | G9: Orange | H9: =INDEX(Hypothèses!$B$4:$B$6,MATCH(G9,Hypothèses!$A$4:$A$6,0)) -> 1 | I9: =ROUNDUP((D9-C9)/H9,0) -> 25 | J9: =IF(INDEX(Recettes!$E:$E,MATCH(F9,Recettes!$A:$A,0))="Oui","Maître",IFERROR("Marchand : "&INDEX(Marchands_recettes!$B:$B,MATCH(F9,Marchands_recettes!$I:$I,0)),"Autre (vendeur / quête / butin)")) -> Marchand : Kelsey Yance | K9: ="Cuisiner "&I9&"× "&E9&" (compétence "&C9&" → "&D9&")" -> Cuisiner 25× Barracuda luisant cuit (compétence 240 → 265) | L9: =COUNTIFS(Plan_matériaux!$A:$A,A9,Plan_matériaux!$J:$J,"À renseigner") -> 0 | M9: Kelsey Yance (Vallée de Strangleronce, 28,2 / 74,3) - Recette : Barracuda luisant cuit, compétence 225 - QuestieDB, à confirmer en jeu.
A10: 9 | B10: =INDEX(Rangs_métier!$A$2:$A$5,MATCH(C10,Rangs_métier!$B$2:$B$5,1)) -> Artisan | C10: 265 | D10: 285 | E10: Barracuda luisant cuit | F10: 13927 | G10: Jaune | H10: =INDEX(Hypothèses!$B$4:$B$6,MATCH(G10,Hypothèses!$A$4:$A$6,0)) -> 0.75 | I10: =ROUNDUP((D10-C10)/H10,0) -> 27 | J10: =IF(INDEX(Recettes!$E:$E,MATCH(F10,Recettes!$A:$A,0))="Oui","Maître",IFERROR("Marchand : "&INDEX(Marchands_recettes!$B:$B,MATCH(F10,Marchands_recettes!$I:$I,0)),"Autre (vendeur / quête / butin)")) -> Marchand : Kelsey Yance | K10: ="Cuisiner "&I10&"× "&E10&" (compétence "&C10&" → "&D10&")" -> Cuisiner 27× Barracuda luisant cuit (compétence 265 → 285) | L10: =COUNTIFS(Plan_matériaux!$A:$A,A10,Plan_matériaux!$J:$J,"À renseigner") -> 0 | M10: Voir quête 8.
A11: 10 | B11: =INDEX(Rangs_métier!$A$2:$A$5,MATCH(C11,Rangs_métier!$B$2:$B$5,1)) -> Artisan | C11: 285 | D11: 300 | E11: Barracuda luisant cuit | F11: 13927 | G11: Vert | H11: =INDEX(Hypothèses!$B$4:$B$6,MATCH(G11,Hypothèses!$A$4:$A$6,0)) -> 0.25 | I11: =ROUNDUP((D11-C11)/H11,0) -> 60 | J11: =IF(INDEX(Recettes!$E:$E,MATCH(F11,Recettes!$A:$A,0))="Oui","Maître",IFERROR("Marchand : "&INDEX(Marchands_recettes!$B:$B,MATCH(F11,Marchands_recettes!$I:$I,0)),"Autre (vendeur / quête / butin)")) -> Marchand : Kelsey Yance | K11: ="Cuisiner "&I11&"× "&E11&" (compétence "&C11&" → "&D11&")" -> Cuisiner 60× Barracuda luisant cuit (compétence 285 → 300) | L11: =COUNTIFS(Plan_matériaux!$A:$A,A11,Plan_matériaux!$J:$J,"À renseigner") -> 0 | M11: Voir quête 8.

Sheet Plan_matériaux
A1: Quête n° | B1: Recette | C1: id_ingrédient | D1: Ingrédient | E1: Qté par craft | F1: Nb de crafts | G1: Total à récolter | H1: Type de source | I1: Zone (1re source) | J1: Statut source
A2: 1 | B2: =INDEX(Plan_quêtes!$E$2:$E$11,A2) -> Aile de chauve-souris croustillante | C2: 12223 | D2: Aile de chauve-souris charnue | E2: =SUMIFS(Composants!$E:$E,Composants!$A:$A,INDEX(Plan_quêtes!$F$2:$F$11,A2),Composants!$C:$C,C2) -> 1 | F2: =INDEX(Plan_quêtes!$I$2:$I$11,A2) -> 44 | G2: =E2*F2 -> 44 | H2: =IFERROR(INDEX(Sources!$C:$C,MATCH(C2,Sources!$A:$A,0)),"—") -> Monstre | I2: =IFERROR(IF(INDEX(Sources!$E:$E,MATCH(C2,Sources!$A:$A,0))="","",INDEX(Sources!$E:$E,MATCH(C2,Sources!$A:$A,0))),"—") -> Tirisfal Glades | J2: =INDEX(Ingrédients!$F$2:$F$98,MATCH(C2,Ingrédients!$A$2:$A$98,0)) -> Renseigné
A3: 1 | B3: =INDEX(Plan_quêtes!$E$2:$E$11,A3) -> Aile de chauve-souris croustillante | C3: 2678 | D3: Epices douces | E3: =SUMIFS(Composants!$E:$E,Composants!$A:$A,INDEX(Plan_quêtes!$F$2:$F$11,A3),Composants!$C:$C,C3) -> 1 | F3: =INDEX(Plan_quêtes!$I$2:$I$11,A3) -> 44 | G3: =E3*F3 -> 44 | H3: =IFERROR(INDEX(Sources!$C:$C,MATCH(C3,Sources!$A:$A,0)),"—") -> Vendeur | I3: =IFERROR(IF(INDEX(Sources!$E:$E,MATCH(C3,Sources!$A:$A,0))="","",INDEX(Sources!$E:$E,MATCH(C3,Sources!$A:$A,0))),"—") -> Tirisfal Glades | J3: =INDEX(Ingrédients!$F$2:$F$98,MATCH(C3,Ingrédients!$A$2:$A$98,0)) -> Renseigné
A4: 2 | B4: =INDEX(Plan_quêtes!$E$2:$E$11,A4) -> Viande d'ours fumée | C4: 3173 | D4: Viande d'ours | E4: =SUMIFS(Composants!$E:$E,Composants!$A:$A,INDEX(Plan_quêtes!$F$2:$F$11,A4),Composants!$C:$C,C4) -> 1 | F4: =INDEX(Plan_quêtes!$I$2:$I$11,A4) -> 35 | G4: =E4*F4 -> 35 | H4: =IFERROR(INDEX(Sources!$C:$C,MATCH(C4,Sources!$A:$A,0)),"—") -> Monstre | I4: =IFERROR(IF(INDEX(Sources!$E:$E,MATCH(C4,Sources!$A:$A,0))="","",INDEX(Sources!$E:$E,MATCH(C4,Sources!$A:$A,0))),"—") -> Darkshore | J4: =INDEX(Ingrédients!$F$2:$F$98,MATCH(C4,Ingrédients!$A$2:$A$98,0)) -> Renseigné
A5: 3 | B5: =INDEX(Plan_quêtes!$E$2:$E$11,A5) -> Côtes de porc séchées | C5: 2677 | D5: Côtes de sanglier | E5: =SUMIFS(Composants!$E:$E,Composants!$A:$A,INDEX(Plan_quêtes!$F$2:$F$11,A5),Composants!$C:$C,C5) -> 1 | F5: =INDEX(Plan_quêtes!$I$2:$I$11,A5) -> 40 | G5: =E5*F5 -> 40 | H5: =IFERROR(INDEX(Sources!$C:$C,MATCH(C5,Sources!$A:$A,0)),"—") -> Monstre | I5: =IFERROR(IF(INDEX(Sources!$E:$E,MATCH(C5,Sources!$A:$A,0))="","",INDEX(Sources!$E:$E,MATCH(C5,Sources!$A:$A,0))),"—") -> Loch Modan | J5: =INDEX(Ingrédients!$F$2:$F$98,MATCH(C5,Ingrédients!$A$2:$A$98,0)) -> Renseigné
A6: 3 | B6: =INDEX(Plan_quêtes!$E$2:$E$11,A6) -> Côtes de porc séchées | C6: 2678 | D6: Epices douces | E6: =SUMIFS(Composants!$E:$E,Composants!$A:$A,INDEX(Plan_quêtes!$F$2:$F$11,A6),Composants!$C:$C,C6) -> 1 | F6: =INDEX(Plan_quêtes!$I$2:$I$11,A6) -> 40 | G6: =E6*F6 -> 40 | H6: =IFERROR(INDEX(Sources!$C:$C,MATCH(C6,Sources!$A:$A,0)),"—") -> Vendeur | I6: =IFERROR(IF(INDEX(Sources!$E:$E,MATCH(C6,Sources!$A:$A,0))="","",INDEX(Sources!$E:$E,MATCH(C6,Sources!$A:$A,0))),"—") -> Tirisfal Glades | J6: =INDEX(Ingrédients!$F$2:$F$98,MATCH(C6,Ingrédients!$A$2:$A$98,0)) -> Renseigné
A7: 4 | B7: =INDEX(Plan_quêtes!$E$2:$E$11,A7) -> Gombo de crocilisque | C7: 3667 | D7: Viande de crocilisque tendre | E7: =SUMIFS(Composants!$E:$E,Composants!$A:$A,INDEX(Plan_quêtes!$F$2:$F$11,A7),Composants!$C:$C,C7) -> 1 | F7: =INDEX(Plan_quêtes!$I$2:$I$11,A7) -> 40 | G7: =E7*F7 -> 40 | H7: =IFERROR(INDEX(Sources!$C:$C,MATCH(C7,Sources!$A:$A,0)),"—") -> Monstre | I7: =IFERROR(IF(INDEX(Sources!$E:$E,MATCH(C7,Sources!$A:$A,0))="","",INDEX(Sources!$E:$E,MATCH(C7,Sources!$A:$A,0))),"—") -> Wetlands | J7: =INDEX(Ingrédients!$F$2:$F$98,MATCH(C7,Ingrédients!$A$2:$A$98,0)) -> Renseigné
A8: 4 | B8: =INDEX(Plan_quêtes!$E$2:$E$11,A8) -> Gombo de crocilisque | C8: 2692 | D8: Epices fortes | E8: =SUMIFS(Composants!$E:$E,Composants!$A:$A,INDEX(Plan_quêtes!$F$2:$F$11,A8),Composants!$C:$C,C8) -> 1 | F8: =INDEX(Plan_quêtes!$I$2:$I$11,A8) -> 40 | G8: =E8*F8 -> 40 | H8: =IFERROR(INDEX(Sources!$C:$C,MATCH(C8,Sources!$A:$A,0)),"—") -> Vendeur | I8: =IFERROR(IF(INDEX(Sources!$E:$E,MATCH(C8,Sources!$A:$A,0))="","",INDEX(Sources!$E:$E,MATCH(C8,Sources!$A:$A,0))),"—") -> Undercity | J8: =INDEX(Ingrédients!$F$2:$F$98,MATCH(C8,Ingrédients!$A$2:$A$98,0)) -> Renseigné
A9: 5 | B9: =INDEX(Plan_quêtes!$E$2:$E$11,A9) -> Délicieux steak de lion | C9: 3731 | D9: Viande de lion | E9: =SUMIFS(Composants!$E:$E,Composants!$A:$A,INDEX(Plan_quêtes!$F$2:$F$11,A9),Composants!$C:$C,C9) -> 2 | F9: =INDEX(Plan_quêtes!$I$2:$I$11,A9) -> 30 | G9: =E9*F9 -> 60 | H9: =IFERROR(INDEX(Sources!$C:$C,MATCH(C9,Sources!$A:$A,0)),"—") -> Monstre | I9: =IFERROR(IF(INDEX(Sources!$E:$E,MATCH(C9,Sources!$A:$A,0))="","",INDEX(Sources!$E:$E,MATCH(C9,Sources!$A:$A,0))),"—") -> Hillsbrad Foothills | J9: =INDEX(Ingrédients!$F$2:$F$98,MATCH(C9,Ingrédients!$A$2:$A$98,0)) -> Renseigné
A10: 5 | B10: =INDEX(Plan_quêtes!$E$2:$E$11,A10) -> Délicieux steak de lion | C10: 3713 | D10: Epices apaisantes | E10: =SUMIFS(Composants!$E:$E,Composants!$A:$A,INDEX(Plan_quêtes!$F$2:$F$11,A10),Composants!$C:$C,C10) -> 1 | F10: =INDEX(Plan_quêtes!$I$2:$I$11,A10) -> 30 | G10: =E10*F10 -> 30 | H10: =IFERROR(INDEX(Sources!$C:$C,MATCH(C10,Sources!$A:$A,0)),"—") -> Vendeur | I10: =IFERROR(IF(INDEX(Sources!$E:$E,MATCH(C10,Sources!$A:$A,0))="","",INDEX(Sources!$E:$E,MATCH(C10,Sources!$A:$A,0))),"—") -> Undercity | J10: =INDEX(Ingrédients!$F$2:$F$98,MATCH(C10,Ingrédients!$A$2:$A$98,0)) -> Renseigné
A11: 6 | B11: =INDEX(Plan_quêtes!$E$2:$E$11,A11) -> Bonne vieille viande de brochepâle | C11: 769 | D11: Morceau de viande de sanglier | E11: =SUMIFS(Composants!$E:$E,Composants!$A:$A,INDEX(Plan_quêtes!$F$2:$F$11,A11),Composants!$C:$C,C11) -> 2 | F11: =INDEX(Plan_quêtes!$I$2:$I$11,A11) -> 10 | G11: =E11*F11 -> 20 | H11: =IFERROR(INDEX(Sources!$C:$C,MATCH(C11,Sources!$A:$A,0)),"—") -> Monstre | I11: =IFERROR(IF(INDEX(Sources!$E:$E,MATCH(C11,Sources!$A:$A,0))="","",INDEX(Sources!$E:$E,MATCH(C11,Sources!$A:$A,0))),"—") -> Elwynn Forest | J11: =INDEX(Ingrédients!$F$2:$F$98,MATCH(C11,Ingrédients!$A$2:$A$98,0)) -> Renseigné
A12: 6 | B12: =INDEX(Plan_quêtes!$E$2:$E$11,A12) -> Bonne vieille viande de brochepâle | C12: 2678 | D12: Epices douces | E12: =SUMIFS(Composants!$E:$E,Composants!$A:$A,INDEX(Plan_quêtes!$F$2:$F$11,A12),Composants!$C:$C,C12) -> 1 | F12: =INDEX(Plan_quêtes!$I$2:$I$11,A12) -> 10 | G12: =E12*F12 -> 10 | H12: =IFERROR(INDEX(Sources!$C:$C,MATCH(C12,Sources!$A:$A,0)),"—") -> Vendeur | I12: =IFERROR(IF(INDEX(Sources!$E:$E,MATCH(C12,Sources!$A:$A,0))="","",INDEX(Sources!$E:$E,MATCH(C12,Sources!$A:$A,0))),"—") -> Tirisfal Glades | J12: =INDEX(Ingrédients!$F$2:$F$98,MATCH(C12,Ingrédients!$A$2:$A$98,0)) -> Renseigné
A13: 7 | B13: =INDEX(Plan_quêtes!$E$2:$E$11,A13) -> Saucisse d'araignée | C13: 12205 | D13: Viande d'araignée blanche | E13: =SUMIFS(Composants!$E:$E,Composants!$A:$A,INDEX(Plan_quêtes!$F$2:$F$11,A13),Composants!$C:$C,C13) -> 2 | F13: =INDEX(Plan_quêtes!$I$2:$I$11,A13) -> 40 | G13: =E13*F13 -> 80 | H13: =IFERROR(INDEX(Sources!$C:$C,MATCH(C13,Sources!$A:$A,0)),"—") -> Monstre | I13: =IFERROR(IF(INDEX(Sources!$E:$E,MATCH(C13,Sources!$A:$A,0))="","",INDEX(Sources!$E:$E,MATCH(C13,Sources!$A:$A,0))),"—") -> Dustwallow Marsh | J13: =INDEX(Ingrédients!$F$2:$F$98,MATCH(C13,Ingrédients!$A$2:$A$98,0)) -> Renseigné
... A19: 10 | B19: =INDEX(Plan_quêtes!$E$2:$E$11,A19) -> Barracuda luisant cuit | C19: 3713 | D19: Epices apaisantes | E19: =SUMIFS(Composants!$E:$E,Composants!$A:$A,INDEX(Plan_quêtes!$F$2:$F$11,A19),Composants!$C:$C,C19) -> 1 | F19: =INDEX(Plan_quêtes!$I$2:$I$11,A19) -> 60 | G19: =E19*F19 -> 60 | H19: =IFERROR(INDEX(Sources!$C:$C,MATCH(C19,Sources!$A:$A,0)),"—") -> Vendeur | I19: =IFERROR(IF(INDEX(Sources!$E:$E,MATCH(C19,Sources!$A:$A,0))="","",INDEX(Sources!$E:$E,MATCH(C19,Sources!$A:$A,0))),"—") -> Undercity | J19: =INDEX(Ingrédients!$F$2:$F$98,MATCH(C19,Ingrédients!$A$2:$A$98,0)) -> Renseigné

Sheet Hypothèses
A1: Hypothèses du plan de progression
A3: Couleur de la recette | B3: Chance de gain de compétence par craft
A4: Orange | B4: 1
A5: Jaune | B5: 0.75
A6: Vert | B6: 0.25
A9: Les chances (100 % / 75 % / 25 %) sont des valeurs de référence de WoW Classic, pas des valeurs confirmées pour Forever : modifiables dans les cellules jaunes.
A10: La source dit seulement : orange = toujours, jaune = souvent, vert = rarement, gris = jamais.
A11: Règle du plan : à chaque point de compétence, choisir la recette de meilleure couleur (orange > jaune > vert) ; à couleur égale, privilégier celle dont tous les ingrédients ont une source renseignée, puis la plus récemment débloquée (progression naturelle, ingrédients de niveau adapté), puis celle qui reste utile le plus longtemps.
A12: Recettes apprises chez un maître : la source ne donne pas le niveau orange. Hypothèse : orange = jaune − 40 (écart observé sur plusieurs recettes Classic, à confirmer en jeu).
A13: Cible du plan : compétence 300. Les kits de feu de camp sont exclus. Les 12 recettes « À vérifier » sont exclues.
A14: Non pris en compte : prix, coût des recettes vendues, niveau du personnage requis, disponibilité réelle des recettes de vendeur ou de quête.
A15: Nombre de crafts = arrondi supérieur de (compétence fin − début) / chance.

Sheet Composants
A1: id_recette | B1: Recette | C1: id_ingrédient | D1: Ingrédient | E1: Quantité
A2: 279981 | B2: Kit de feu de camp basique | C2: 4470 | D2: Bois simple | E2: 1
A3: 249871 | B3: Frappé venimeux | C3: 159 | D3: Eau de source | E3: 1
A4: 249871 | B4: Frappé venimeux | C4: 2678 | D4: Epices douces | E4: 1
A5: 249871 | B5: Frappé venimeux | C5: 1475 | D5: Petite glande à venin | E5: 1
A6: 263509 | B6: Soufflé de Mur-Céleste | C6: 6889 | D6: Petit oeuf | E6: 2
A7: 263509 | B7: Soufflé de Mur-Céleste | C7: 10284 | D7: Farine simple | E7: 1
A8: 818 | B8: Feu de camp basique | C8: 4470 | D8: Bois simple | E8: 1
A9: 249865 | B9: Thé de sérénité | C9: 159 | D9: Eau de source | E9: 1
A10: 249865 | B10: Thé de sérénité | C10: 2447 | D10: Pacifique | E10: 2
A11: 263512 | B11: Bouchées à la chair de pinces | C11: 2675 | D11: Pince de clampant | E11: 1
A12: 263512 | B12: Bouchées à la chair de pinces | C12: 10284 | D12: Farine simple | E12: 1
A13: 250079 | B13: Délicieuses bouchées au raptor | C13: 3685 | D13: Oeuf de raptor | E13: 1
... A240: 21023 | B240: Pyro-côtelettes de chimaerok à la Dirge | C240: 21024 | D240: Filet de chimaerok | E240: 1

Sheet Ingrédients
A1: id_ingrédient | B1: Ingrédient | C1: Nb recettes qui l'utilisent | D1: Quantité totale (toutes recettes) | E1: Nb sources renseignées | F1: Statut | G1: Besoin total (plan, compétence 300)
A2: 3404 | B2: Aile de busard | C2: =COUNTIF(Composants!C:C,A2) -> 1 | D2: =SUMIF(Composants!C:C,A2,Composants!E:E) -> 1 | E2: =COUNTIF(Sources!A:A,A2) -> 4 | F2: =IF(E2>0,"Renseigné","À renseigner") -> Renseigné | G2: =SUMIF(Plan_matériaux!$C$2:$C$19,A2,Plan_matériaux!$G$2:$G$19) -> 0
A3: 12223 | B3: Aile de chauve-souris charnue | C3: =COUNTIF(Composants!C:C,A3) -> 1 | D3: =SUMIF(Composants!C:C,A3,Composants!E:E) -> 1 | E3: =COUNTIF(Sources!A:A,A3) -> 1 | F3: =IF(E3>0,"Renseigné","À renseigner") -> Renseigné | G3: =SUMIF(Plan_matériaux!$C$2:$C$19,A3,Plan_matériaux!$G$2:$G$19) -> 44
A4: 1468 | B4: Aileron de murloc | C4: =COUNTIF(Composants!C:C,A4) -> 2 | D4: =SUMIF(Composants!C:C,A4,Composants!E:E) -> 3 | E4: =COUNTIF(Sources!A:A,A4) -> 2 | F4: =IF(E4>0,"Renseigné","À renseigner") -> Renseigné | G4: =SUMIF(Plan_matériaux!$C$2:$C$19,A4,Plan_matériaux!$G$2:$G$19) -> 0
A5: 13754 | B5: Barracuda luisant cru | C5: =COUNTIF(Composants!C:C,A5) -> 1 | D5: =SUMIF(Composants!C:C,A5,Composants!E:E) -> 1 | E5: =COUNTIF(Sources!A:A,A5) -> 5 | F5: =IF(E5>0,"Renseigné","À renseigner") -> Renseigné | G5: =SUMIF(Plan_matériaux!$C$2:$C$19,A5,Plan_matériaux!$G$2:$G$19) -> 112
A6: 2894 | B6: Bière au malt Rhapsody | C6: =COUNTIF(Composants!C:C,A6) -> 1 | D6: =SUMIF(Composants!C:C,A6,Composants!E:E) -> 1 | E6: =COUNTIF(Sources!A:A,A6) -> 0 | F6: =IF(E6>0,"Renseigné","À renseigner") -> À renseigner | G6: =SUMIF(Plan_matériaux!$C$2:$C$19,A6,Plan_matériaux!$G$2:$G$19) -> 0
A7: 11291 | B7: Bois d'étoile | C7: =COUNTIF(Composants!C:C,A7) -> 1 | D7: =SUMIF(Composants!C:C,A7,Composants!E:E) -> 1 | E7: =COUNTIF(Sources!A:A,A7) -> 1 | F7: =IF(E7>0,"Renseigné","À renseigner") -> Renseigné | G7: =SUMIF(Plan_matériaux!$C$2:$C$19,A7,Plan_matériaux!$G$2:$G$19) -> 0
A8: 4470 | B8: Bois simple | C8: =COUNTIF(Composants!C:C,A8) -> 2 | D8: =SUMIF(Composants!C:C,A8,Composants!E:E) -> 2 | E8: =COUNTIF(Sources!A:A,A8) -> 2 | F8: =IF(E8>0,"Renseigné","À renseigner") -> Renseigné | G8: =SUMIF(Plan_matériaux!$C$2:$C$19,A8,Plan_matériaux!$G$2:$G$19) -> 0
A9: 272941 | B9: Bûches épaisses | C9: =COUNTIF(Composants!C:C,A9) -> 1 | D9: =SUMIF(Composants!C:C,A9,Composants!E:E) -> 1 | E9: =COUNTIF(Sources!A:A,A9) -> 0 | F9: =IF(E9>0,"Renseigné","À renseigner") -> À renseigner | G9: =SUMIF(Plan_matériaux!$C$2:$C$19,A9,Plan_matériaux!$G$2:$G$19) -> 0
A10: 1081 | B10: Chair croustillante d'araignée | C10: =COUNTIF(Composants!C:C,A10) -> 1 | D10: =SUMIF(Composants!C:C,A10,Composants!E:E) -> 1 | E10: =COUNTIF(Sources!A:A,A10) -> 1 | F10: =IF(E10>0,"Renseigné","À renseigner") -> Renseigné | G10: =SUMIF(Plan_matériaux!$C$2:$C$19,A10,Plan_matériaux!$G$2:$G$19) -> 0
A11: 2674 | B11: Chair de clampant | C11: =COUNTIF(Composants!C:C,A11) -> 1 | D11: =SUMIF(Composants!C:C,A11,Composants!E:E) -> 1 | E11: =COUNTIF(Sources!A:A,A11) -> 3 | F11: =IF(E11>0,"Renseigné","À renseigner") -> Renseigné | G11: =SUMIF(Plan_matériaux!$C$2:$C$19,A11,Plan_matériaux!$G$2:$G$19) -> 0
A12: 5503 | B12: Chair de palourde | C12: =COUNTIF(Composants!C:C,A12) -> 2 | D12: =SUMIF(Composants!C:C,A12,Composants!E:E) -> 2 | E12: =COUNTIF(Sources!A:A,A12) -> 3 | F12: =IF(E12>0,"Renseigné","À renseigner") -> Renseigné | G12: =SUMIF(Plan_matériaux!$C$2:$C$19,A12,Plan_matériaux!$G$2:$G$19) -> 0
A13: 4655 | B13: Chair de palourde géante | C13: =COUNTIF(Composants!C:C,A13) -> 1 | D13: =SUMIF(Composants!C:C,A13,Composants!E:E) -> 1 | E13: =COUNTIF(Sources!A:A,A13) -> 1 | F13: =IF(E13>0,"Renseigné","À renseigner") -> Renseigné | G13: =SUMIF(Plan_matériaux!$C$2:$C$19,A13,Plan_matériaux!$G$2:$G$19) -> 0
... A110: 21024 | B110: Filet de chimaerok | C110: =COUNTIF(Composants!C:C,A110) -> 1 | D110: =SUMIF(Composants!C:C,A110,Composants!E:E) -> 1 | E110: =COUNTIF(Sources!A:A,A110) -> 1 | F110: =IF(E110>0,"Renseigné","À renseigner") -> Renseigné | G110: =SUMIF(Plan_matériaux!$C$2:$C$19,A110,Plan_matériaux!$G$2:$G$19) -> 0

Sheet Sources
A1: id_ingrédient | B1: Ingrédient | C1: Type de source | D1: Source (monstre / objet / pêche / PNJ) | E1: Zone (nom anglais) | F1: Niveau mob (min) | G1: Niveau mob (max) | H1: Taux de butin / de prise (%) | I1: Référence | J1: Notes
A2: 3173 | B2: Viande d'ours | C2: Monstre | D2: Bears | E2: Darkshore | F2: 11 | G2: 17 | I2: Wowhead Classic — Best Cooking Ingredient Farming Spots (1.15.8) | J2: Pas les faux ours (druides) du sud de Silverpine
A3: 3173 | B3: Viande d'ours | C3: Monstre | D3: Bears | E3: Loch Modan | F3: 11 | G3: 17 | I3: Wowhead Classic — Best Cooking Ingredient Farming Spots (1.15.8) | J3: Pas les faux ours (druides) du sud de Silverpine
A4: 3173 | B4: Viande d'ours | C4: Monstre | D4: Bears | E4: Silverpine Forest | F4: 11 | G4: 17 | I4: Wowhead Classic — Best Cooking Ingredient Farming Spots (1.15.8) | J4: Pas les faux ours (druides) du sud de Silverpine
A5: 3730 | B5: Viande de grand ours | C5: Monstre | D5: Bears (Evil Grizzly à Hillsbrad) | E5: Ashenvale | F5: 21 | G5: 30 | I5: Wowhead Classic — Best Cooking Ingredient Farming Spots (1.15.8)
A6: 3730 | B6: Viande de grand ours | C6: Monstre | D6: Bears (Evil Grizzly à Hillsbrad) | E6: Hillsbrad Foothills | F6: 21 | G6: 30 | I6: Wowhead Classic — Best Cooking Ingredient Farming Spots (1.15.8)
A7: 3172 | B7: Tripes de sanglier | C7: Monstre | D7: Mountain Boar, Rugged Boar, Elder Mountain Boar | E7: Loch Modan | I7: Wowhead Classic — Best Cooking Ingredient Farming Spots (1.15.8)
A8: 2677 | B8: Côtes de sanglier | C8: Monstre | D8: Boars (Mountain Boar à Loch Modan ; Goretusk à Westfall) | E8: Loch Modan | F8: 10 | G8: 17 | I8: Wowhead Classic — Best Cooking Ingredient Farming Spots (1.15.8)
A9: 2677 | B9: Côtes de sanglier | C9: Monstre | D9: Boars (Mountain Boar à Loch Modan ; Goretusk à Westfall) | E9: Westfall | F9: 10 | G9: 17 | I9: Wowhead Classic — Best Cooking Ingredient Farming Spots (1.15.8)
A10: 3404 | B10: Aile de busard | C10: Monstre | D10: Carrion Birds (vautours) | E10: Arathi Highlands | F10: 31 | G10: 49 | I10: Wowhead Classic — Best Cooking Ingredient Farming Spots (1.15.8) | J10: Tanaris : rocs plus dispersés
A11: 3404 | B11: Aile de busard | C11: Monstre | D11: Carrion Birds (vautours) | E11: Desolace | F11: 31 | G11: 49 | I11: Wowhead Classic — Best Cooking Ingredient Farming Spots (1.15.8) | J11: Tanaris : rocs plus dispersés
A12: 3404 | B12: Aile de busard | C12: Monstre | D12: Carrion Birds (vautours) | E12: Badlands | F12: 31 | G12: 49 | I12: Wowhead Classic — Best Cooking Ingredient Farming Spots (1.15.8) | J12: Tanaris : rocs plus dispersés
A13: 3404 | B13: Aile de busard | C13: Monstre | D13: Carrion Birds (vautours) | E13: Tanaris | F13: 31 | G13: 49 | I13: Wowhead Classic — Best Cooking Ingredient Farming Spots (1.15.8) | J13: Tanaris : rocs plus dispersés
A14: 769 | B14: Morceau de viande de sanglier | C14: Monstre | D14: Boars | E14: Elwynn Forest | F14: 5 | G14: 17 | I14: Wowhead Classic — Best Cooking Ingredient Farming Spots (1.15.8)
A15: 769 | B15: Morceau de viande de sanglier | C15: Monstre | D15: Boars | E15: Loch Modan | F15: 5 | G15: 17 | I15: Wowhead Classic — Best Cooking Ingredient Farming Spots (1.15.8)
A16: 769 | B16: Morceau de viande de sanglier | C16: Monstre | D16: Boars | E16: Durotar | F16: 5 | G16: 17 | I16: Wowhead Classic — Best Cooking Ingredient Farming Spots (1.15.8)
A17: 5503 | B17: Chair de palourde | C17: Monstre | D17: Threshers, Crawlers, Murlocs, Naga (butin : petit coquillage) | E17: Darkshore | F17: 5 | G17: 22 | I17: Wowhead Classic — Best Cooking Ingredient Farming Spots (1.15.8) | J17: Aussi dans des coquilles géantes immergées (Barrens, Westfall, Ashenvale, Darkshore)
A18: 5503 | B18: Chair de palourde | C18: Monstre | D18: Threshers, Crawlers, Murlocs, Naga (butin : petit coquillage) | E18: Westfall | F18: 5 | G18: 22 | I18: Wowhead Classic — Best Cooking Ingredient Farming Spots (1.15.8) | J18: Aussi dans des coquilles géantes immergées (Barrens, Westfall, Ashenvale, Darkshore)
A19: 5503 | B19: Chair de palourde | C19: Monstre | D19: Threshers, Crawlers, Murlocs, Naga (butin : petit coquillage) | E19: Ashenvale | F19: 5 | G19: 22 | I19: Wowhead Classic — Best Cooking Ingredient Farming Spots (1.15.8) | J19: Aussi dans des coquilles géantes immergées (Barrens, Westfall, Ashenvale, Darkshore)
A20: 2673 | B20: Viande de coyote | C20: Monstre | D20: Coyote, Coyote Packleader | E20: Westfall | F20: 10 | G20: 12 | I20: Wowhead Classic — Best Cooking Ingredient Farming Spots (1.15.8)
A21: 2886 | B21: Côtes de sanglier des rochers | C21: Monstre | D21: Crag Boars | E21: Dun Morogh | F21: 6 | G21: 10 | I21: Wowhead Classic — Best Cooking Ingredient Farming Spots (1.15.8)
A22: 2675 | B22: Pince de clampant | C22: Monstre | D22: Crawlers | E22: Darkshore | F22: 10 | G22: 20 | I22: Wowhead Classic — Best Cooking Ingredient Farming Spots (1.15.8) | J22: Ashenvale : côte de Zoram Strand
A23: 2675 | B23: Pince de clampant | C23: Monstre | D23: Crawlers | E23: Westfall | F23: 10 | G23: 20 | I23: Wowhead Classic — Best Cooking Ingredient Farming Spots (1.15.8) | J23: Ashenvale : côte de Zoram Strand
A24: 2675 | B24: Pince de clampant | C24: Monstre | D24: Crawlers | E24: Ashenvale | F24: 10 | G24: 20 | I24: Wowhead Classic — Best Cooking Ingredient Farming Spots (1.15.8) | J24: Ashenvale : côte de Zoram Strand
A25: 2674 | B25: Chair de clampant | C25: Monstre | D25: Crawlers | E25: Darkshore | F25: 10 | G25: 20 | I25: Wowhead Classic — Best Cooking Ingredient Farming Spots (1.15.8) | J25: Ashenvale : côte de Zoram Strand
A26: 2674 | B26: Chair de clampant | C26: Monstre | D26: Crawlers | E26: Westfall | F26: 10 | G26: 20 | I26: Wowhead Classic — Best Cooking Ingredient Farming Spots (1.15.8) | J26: Ashenvale : côte de Zoram Strand
A27: 2674 | B27: Chair de clampant | C27: Monstre | D27: Crawlers | E27: Ashenvale | F27: 10 | G27: 20 | I27: Wowhead Classic — Best Cooking Ingredient Farming Spots (1.15.8) | J27: Ashenvale : côte de Zoram Strand
A28: 1081 | B28: Chair croustillante d'araignée | C28: Monstre | D28: Murloc Scavenger, Giant Tarantula | E28: Redridge Mountains | F28: 15 | G28: 20 | I28: Wowhead Classic — Best Cooking Ingredient Farming Spots (1.15.8)
A29: 2924 | B29: Viande de crocilisque | C29: Monstre | D29: Loch Crocolisk | E29: Loch Modan | F29: 14 | G29: 15 | I29: Wowhead Classic — Best Cooking Ingredient Farming Spots (1.15.8)
A30: 5051 | B30: Rat fouisseur | C30: Monstre | D30: Dig Rat (entouré de nains de niveau 21-25) | E30: The Barrens | F30: 21 | G30: 25 | I30: Wowhead Classic — Best Cooking Ingredient Farming Spots (1.15.8) | J30: Les rats sont niveau 1 ; niveau 21-25 = les nains autour de Bael Modan
A31: 4655 | B31: Chair de palourde géante | C31: Objet du monde | D31: Giant Clam (coquille géante immergée, à l'ouest de Grom'gol) | E31: Stranglethorn Vale | F31: 35 | G31: 37 | I31: Wowhead Classic — Best Cooking Ingredient Farming Spots (1.15.8) | J31: Murlocs Saltscale élites 35-37 à proximité
A32: 12207 | B32: Oeuf géant | C32: Monstre | D32: Carrion Birds, Owls, Owlbeasts | E32: Tanaris | F32: 41 | G32: 49 | I32: Wowhead Classic — Best Cooking Ingredient Farming Spots (1.15.8)
A33: 12207 | B33: Oeuf géant | C33: Monstre | D33: Carrion Birds, Owls, Owlbeasts | E33: Winterspring | F33: 50 | G33: 59 | I33: Wowhead Classic — Best Cooking Ingredient Farming Spots (1.15.8)
A34: 2251 | B34: Patte d'araignée fondante | C34: Monstre | D34: Spiders (Green Recluse en majorité) | E34: Duskwood | F34: 18 | G34: 36 | I34: Wowhead Classic — Best Cooking Ingredient Farming Spots (1.15.8)
A35: 723 | B35: Foie de Broche-tripes | C35: Monstre | D35: Goretusks | E35: Redridge Mountains | F35: 12 | G35: 17 | I35: Wowhead Classic — Best Cooking Ingredient Farming Spots (1.15.8) | J35: Foie : Redridge et Westfall
A36: 723 | B36: Foie de Broche-tripes | C36: Monstre | D36: Goretusks | E36: Westfall | F36: 12 | G36: 17 | I36: Wowhead Classic — Best Cooking Ingredient Farming Spots (1.15.8) | J36: Foie : Redridge et Westfall
A37: 731 | B37: Groin de Broche-tripes | C37: Monstre | D37: Goretusks (Westfall uniquement) | E37: Westfall | F37: 12 | G37: 17 | I37: Wowhead Classic — Best Cooking Ingredient Farming Spots (1.15.8) | J37: Groin : Westfall uniquement
A38: 12204 | B38: Viande de kodo épaisse | C38: Monstre | D38: Aged Kodo, Dying Kodo, Ancient Kodo | E38: Desolace | F38: 34 | G38: 37 | I38: Wowhead Classic — Best Cooking Ingredient Farming Spots (1.15.8) | J38: Concentration au cimetière des kodos
A39: 5467 | B39: Viande de kodo | C39: Monstre | D39: Kodos | E39: Mulgore | F39: 7 | G39: 26 | I39: Wowhead Classic — Best Cooking Ingredient Farming Spots (1.15.8)
A40: 5467 | B40: Viande de kodo | C40: Monstre | D40: Kodos | E40: The Barrens | F40: 7 | G40: 26 | I40: Wowhead Classic — Best Cooking Ingredient Farming Spots (1.15.8)
A41: 1015 | B41: Steak de loup | C41: Monstre | D41: Wolves | E41: Duskwood | F41: 19 | G41: 28 | I41: Wowhead Classic — Best Cooking Ingredient Farming Spots (1.15.8) | J41: Aussi sur les worgs de Shadowfang Keep
A42: 3731 | B42: Viande de lion | C42: Monstre | D42: Starving Mountain Lion | E42: Hillsbrad Foothills | F42: 23 | G42: 24 | I42: Wowhead Classic — Best Cooking Ingredient Farming Spots (1.15.8)
A43: 12223 | B43: Aile de chauve-souris charnue | C43: Monstre | D43: Giant Nightbat, Vampiric Nightbat | E43: Tirisfal Glades | F43: 6 | G43: 8 | I43: Wowhead Classic — Best Cooking Ingredient Farming Spots (1.15.8) | J43: Aussi à Shadowfang Keep
A44: 730 | B44: Oeil de murloc | C44: Monstre | D44: Murlocs | E44: Westfall | F44: 11 | G44: 25 | I44: Wowhead Classic — Best Cooking Ingredient Farming Spots (1.15.8) | J44: Taux de butin croissant avec le niveau du murloc
A45: 1468 | B45: Aileron de murloc | C45: Monstre | D45: Murlocs | E45: Redridge Mountains | F45: 16 | G45: 25 | I45: Wowhead Classic — Best Cooking Ingredient Farming Spots (1.15.8)
A46: 1468 | B46: Aileron de murloc | C46: Monstre | D46: Murlocs | E46: Ashenvale | F46: 16 | G46: 25 | I46: Wowhead Classic — Best Cooking Ingredient Farming Spots (1.15.8)
A47: 12037 | B47: Viande mystère | C47: Monstre | D47: Carrion Birds, Crocolisks, Hyenas, Scorpids (Dustwallow Crocolisk à Dustwallow) | E47: Desolace | F47: 30 | G47: 50 | I47: Wowhead Classic — Best Cooking Ingredient Farming Spots (1.15.8) | J47: Tombe aussi dans de nombreuses autres zones
A48: 12037 | B48: Viande mystère | C48: Monstre | D48: Carrion Birds, Crocolisks, Hyenas, Scorpids (Dustwallow Crocolisk à Dustwallow) | E48: Dustwallow Marsh | F48: 30 | G48: 50 | I48: Wowhead Classic — Best Cooking Ingredient Farming Spots (1.15.8) | J48: Tombe aussi dans de nombreuses autres zones
A49: 3685 | B49: Oeuf de raptor | C49: Monstre | D49: Raptors | E49: Wetlands | F49: 22 | G49: 28 | I49: Wowhead Classic — Best Cooking Ingredient Farming Spots (1.15.8)
A50: 3685 | B50: Oeuf de raptor | C50: Monstre | D50: Raptors | E50: Arathi Highlands | F50: 30 | G50: 37 | I50: Wowhead Classic — Best Cooking Ingredient Farming Spots (1.15.8)
A51: 3685 | B51: Oeuf de raptor | C51: Monstre | D51: Raptors | E51: Stranglethorn Vale | F51: 30 | G51: 37 | I51: Wowhead Classic — Best Cooking Ingredient Farming Spots (1.15.8)
A52: 12184 | B52: Chair de raptor | C52: Monstre | D52: Raptors | E52: Arathi Highlands | F52: 30 | G52: 50 | I52: Wowhead Classic — Best Cooking Ingredient Farming Spots (1.15.8)
A53: 12184 | B53: Chair de raptor | C53: Monstre | D53: Raptors | E53: Stranglethorn Vale | F53: 30 | G53: 50 | I53: Wowhead Classic — Best Cooking Ingredient Farming Spots (1.15.8)
A54: 12184 | B54: Chair de raptor | C54: Monstre | D54: Raptors | E54: Un'Goro Crater | F54: 30 | G54: 50 | I54: Wowhead Classic — Best Cooking Ingredient Farming Spots (1.15.8)
A55: 5466 | B55: Dard de scorpide | C55: Monstre | D55: Scorpids | E55: Durotar | F55: 5 | G55: 11 | I55: Wowhead Classic — Best Cooking Ingredient Farming Spots (1.15.8)
A56: 6889 | B56: Petit oeuf | C56: Monstre | D56: Owls, Carrion Birds, Owlbeasts | E56: Teldrassil | F56: 5 | G56: 17 | I56: Wowhead Classic — Best Cooking Ingredient Farming Spots (1.15.8)
A57: 6889 | B57: Petit oeuf | C57: Monstre | D57: Owls, Carrion Birds, Owlbeasts | E57: Westfall | F57: 5 | G57: 17 | I57: Wowhead Classic — Best Cooking Ingredient Farming Spots (1.15.8)
A58: 6889 | B58: Petit oeuf | C58: Monstre | D58: Owls, Carrion Birds, Owlbeasts | E58: Darkshore | F58: 5 | G58: 17 | I58: Wowhead Classic — Best Cooking Ingredient Farming Spots (1.15.8)
A59: 6889 | B59: Petit oeuf | C59: Monstre | D59: Owls, Carrion Birds, Owlbeasts | E59: Mulgore | F59: 5 | G59: 17 | I59: Wowhead Classic — Best Cooking Ingredient Farming Spots (1.15.8)
A60: 4402 | B60: Petit sac de flammes | C60: Monstre | D60: Dragonkin whelps, Faerie Dragons | E60: Dustwallow Marsh | F60: 40 | G60: 48 | I60: Wowhead Classic — Best Cooking Ingredient Farming Spots (1.15.8)
... A63: 5465 | B63: Petite patte d'araignée | C63: Monstre | D63: Spiders (Webwood Lurker à Teldrassil) | E63: Teldrassil | F63: 5 | G63: 11 | I63: Wowhead Classic — Best Cooking Ingredient Farming Spots (1.15.8)
A64: 5468 | B64: Chair tendre de Furie | C64: Monstre | D64: Coastal Frenzy | E64: Darkshore | F64: 14 | G64: 16 | I64: Wowhead Classic — Best Cooking Ingredient Farming Spots (1.15.8) | J64: Aussi Frenzies de Silverpine et des Barrens
A65: 3174 | B65: Ichor d'araignée | C65: Monstre | D65: Cliff/Tree/Forest Lurkers (spiders) | E65: Loch Modan | F65: 10 | G65: 18 | I65: Wowhead Classic — Best Cooking Ingredient Farming Spots (1.15.8)
A66: 5471 | B66: Viande de cerf | C66: Monstre | D66: Stags | E66: Ashenvale | F66: 18 | G66: 27 | I66: Wowhead Classic — Best Cooking Ingredient Farming Spots (1.15.8)
A67: 5471 | B67: Viande de cerf | C67: Monstre | D67: Stags | E67: Stonetalon Mountains | F67: 18 | G67: 27 | I67: Wowhead Classic — Best Cooking Ingredient Farming Spots (1.15.8)
A68: 5469 | B68: Viande de trotteur | C68: Monstre | D68: Striders | E68: Darkshore | F68: 11 | G68: 19 | I68: Wowhead Classic — Best Cooking Ingredient Farming Spots (1.15.8)
A69: 5469 | B69: Viande de trotteur | C69: Monstre | D69: Striders | E69: The Barrens | F69: 11 | G69: 19 | I69: Wowhead Classic — Best Cooking Ingredient Farming Spots (1.15.8)
A70: 729 | B70: Viande filandreuse de vautour | C70: Monstre | D70: Fleshrippers (carrion birds) | E70: Westfall | F70: 10 | G70: 17 | I70: Wowhead Classic — Best Cooking Ingredient Farming Spots (1.15.8)
A71: 2672 | B71: Viande de loup maigre | C71: Monstre | D71: Wolves, Darkhounds | E71: Elwynn Forest | F71: 5 | G71: 12 | I71: Wowhead Classic — Best Cooking Ingredient Farming Spots (1.15.8) | J71: Toutes zones 1-10 sauf Teldrassil et Durotar (liste partielle ici)
A72: 2672 | B72: Viande de loup maigre | C72: Monstre | D72: Wolves, Darkhounds | E72: Dun Morogh | F72: 5 | G72: 12 | I72: Wowhead Classic — Best Cooking Ingredient Farming Spots (1.15.8) | J72: Toutes zones 1-10 sauf Teldrassil et Durotar (liste partielle ici)
A73: 2672 | B73: Viande de loup maigre | C73: Monstre | D73: Wolves, Darkhounds | E73: Mulgore | F73: 5 | G73: 12 | I73: Wowhead Classic — Best Cooking Ingredient Farming Spots (1.15.8) | J73: Toutes zones 1-10 sauf Teldrassil et Durotar (liste partielle ici)
A74: 2672 | B74: Viande de loup maigre | C74: Monstre | D74: Wolves, Darkhounds | E74: Tirisfal Glades | F74: 5 | G74: 12 | I74: Wowhead Classic — Best Cooking Ingredient Farming Spots (1.15.8) | J74: Toutes zones 1-10 sauf Teldrassil et Durotar (liste partielle ici)
A75: 5504 | B75: Chair de palourde relevée | C75: Monstre | D75: Murlocs, Naga (butin : coquillage épais) | E75: Wetlands | F75: 20 | G75: 32 | I75: Wowhead Classic — Best Cooking Ingredient Farming Spots (1.15.8)
A76: 5504 | B76: Chair de palourde relevée | C76: Monstre | D76: Murlocs, Naga (butin : coquillage épais) | E76: Hillsbrad Foothills | F76: 20 | G76: 32 | I76: Wowhead Classic — Best Cooking Ingredient Farming Spots (1.15.8)
A77: 12206 | B77: Viande de crabe tendre | C77: Monstre | D77: Southern Sand Crab, Mud Crab, Giant Mud Crab | E77: Stranglethorn Vale | F77: 40 | G77: 44 | I77: Wowhead Classic — Best Cooking Ingredient Farming Spots (1.15.8)
A78: 12206 | B78: Viande de crabe tendre | C78: Monstre | D78: Southern Sand Crab, Mud Crab, Giant Mud Crab | E78: Swamp of Sorrows | F78: 40 | G78: 44 | I78: Wowhead Classic — Best Cooking Ingredient Farming Spots (1.15.8)
A79: 3667 | B79: Viande de crocilisque tendre | C79: Monstre | D79: Crocolisks | E79: Wetlands | F79: 21 | G79: 26 | I79: Wowhead Classic — Best Cooking Ingredient Farming Spots (1.15.8)
A80: 3667 | B80: Viande de crocilisque tendre | C80: Monstre | D80: Crocolisks | E80: Dustwallow Marsh | F80: 35 | G80: 41 | I80: Wowhead Classic — Best Cooking Ingredient Farming Spots (1.15.8)
A81: 12208 | B81: Viande de loup tendre | C81: Monstre | D81: Wolves, Hyenas | E81: The Hinterlands | F81: 40 | G81: 60 | I81: Wowhead Classic — Best Cooking Ingredient Farming Spots (1.15.8)
A82: 12208 | B82: Viande de loup tendre | C82: Monstre | D82: Wolves, Hyenas | E82: Tanaris | F82: 40 | G82: 60 | I82: Wowhead Classic — Best Cooking Ingredient Farming Spots (1.15.8)
A83: 5470 | B83: Queue de lézard-tonnerre | C83: Monstre | D83: Thunderhawk-type lizards (Thunderhead/Lightning/Thunder Lizards) | E83: The Barrens | F83: 18 | G83: 23 | I83: Wowhead Classic — Best Cooking Ingredient Farming Spots (1.15.8)
A84: 12202 | B84: Viande de tigre | C84: Monstre | D84: Tigers | E84: Stranglethorn Vale | F84: 30 | G84: 38 | I84: Wowhead Classic — Best Cooking Ingredient Farming Spots (1.15.8)
A85: 1080 | B85: Viande de condor coriace | C85: Monstre | D85: Tough Condor | E85: Redridge Mountains | F85: 18 | G85: 19 | I85: Wowhead Classic — Best Cooking Ingredient Farming Spots (1.15.8)
A86: 3712 | B86: Viande de tortue | C86: Monstre | D86: Snapjaw turtles | E86: Hillsbrad Foothills | F86: 30 | G86: 31 | I86: Wowhead Classic — Best Cooking Ingredient Farming Spots (1.15.8) | J86: Tombe sur toutes les tortues niveau 30-50
A87: 12205 | B87: Viande d'araignée blanche | C87: Monstre | D87: Spiders | E87: Dustwallow Marsh | F87: 35 | G87: 39 | I87: Wowhead Classic — Best Cooking Ingredient Farming Spots (1.15.8)
A88: 7974 | B88: Chair de palourde piquante | C88: Monstre | D88: Turtles, Threshers, Makrura, Murlocs, Naga (butin : coquille géante) | E88: Tanaris | F88: 40 | G88: 45 | I88: Wowhead Classic — Best Cooking Ingredient Farming Spots (1.15.8)
A89: 7974 | B89: Chair de palourde piquante | C89: Monstre | D89: Turtles, Threshers, Makrura, Murlocs, Naga (butin : coquille géante) | E89: Dustwallow Marsh | F89: 40 | G89: 45 | I89: Wowhead Classic — Best Cooking Ingredient Farming Spots (1.15.8)
A90: 7974 | B90: Chair de palourde piquante | C90: Monstre | D90: Turtles, Threshers, Makrura, Murlocs, Naga (butin : coquille géante) | E90: Swamp of Sorrows | F90: 40 | G90: 45 | I90: Wowhead Classic — Best Cooking Ingredient Farming Spots (1.15.8)
A91: 6308 | B91: Poisson-chat moustachu cru | C91: Pêche | D91: Eaux douces | E91: All Faction Cities | H91: 25 | I91: Wowhead Classic — Best Fishing Farming Spots (1.15.8) | J91: Eaux intérieures ; pêche min 55 (150 pour éviter les échappées) ; ~25% en ville, ~60% dans les zones 20-30 ; Stonetalon : 60% à l'étang central et à Sun Rock, 40% à Windshear Crag
A92: 6308 | B92: Poisson-chat moustachu cru | C92: Pêche | D92: Eaux douces | E92: Ashenvale | H92: 60 | I92: Wowhead Classic — Best Fishing Farming Spots (1.15.8) | J92: Eaux intérieures ; pêche min 55 (150 pour éviter les échappées) ; ~25% en ville, ~60% dans les zones 20-30 ; Stonetalon : 60% à l'étang central et à Sun Rock, 40% à Windshear Crag
A93: 6308 | B93: Poisson-chat moustachu cru | C93: Pêche | D93: Eaux douces | E93: Duskwood | H93: 60 | I93: Wowhead Classic — Best Fishing Farming Spots (1.15.8) | J93: Eaux intérieures ; pêche min 55 (150 pour éviter les échappées) ; ~25% en ville, ~60% dans les zones 20-30 ; Stonetalon : 60% à l'étang central et à Sun Rock, 40% à Windshear Crag
A94: 6308 | B94: Poisson-chat moustachu cru | C94: Pêche | D94: Eaux douces | E94: Hillsbrad Foothills | H94: 60 | I94: Wowhead Classic — Best Fishing Farming Spots (1.15.8) | J94: Eaux intérieures ; pêche min 55 (150 pour éviter les échappées) ; ~25% en ville, ~60% dans les zones 20-30 ; Stonetalon : 60% à l'étang central et à Sun Rock, 40% à Windshear Crag
A95: 6308 | B95: Poisson-chat moustachu cru | C95: Pêche | D95: Eaux douces | E95: Redridge Mountains | H95: 60 | I95: Wowhead Classic — Best Fishing Farming Spots (1.15.8) | J95: Eaux intérieures ; pêche min 55 (150 pour éviter les échappées) ; ~25% en ville, ~60% dans les zones 20-30 ; Stonetalon : 60% à l'étang central et à Sun Rock, 40% à Windshear Crag
A96: 6308 | B96: Poisson-chat moustachu cru | C96: Pêche | D96: Eaux douces | E96: Stonetalon Mountains | H96: 60 | I96: Wowhead Classic — Best Fishing Farming Spots (1.15.8) | J96: Eaux intérieures ; pêche min 55 (150 pour éviter les échappées) ; ~25% en ville, ~60% dans les zones 20-30 ; Stonetalon : 60% à l'étang central et à Sun Rock, 40% à Windshear Crag
A97: 6308 | B97: Poisson-chat moustachu cru | C97: Pêche | D97: Eaux douces | E97: Wetlands | H97: 60 | I97: Wowhead Classic — Best Fishing Farming Spots (1.15.8) | J97: Eaux intérieures ; pêche min 55 (150 pour éviter les échappées) ; ~25% en ville, ~60% dans les zones 20-30 ; Stonetalon : 60% à l'étang central et à Sun Rock, 40% à Windshear Crag
A98: 6291 | B98: Goujon brillant cru | C98: Pêche | D98: Eaux douces (étangs, rivières, lacs) | E98: All 1-10 zones | H98: 60 | I98: Wowhead Classic — Best Fishing Farming Spots (1.15.8) | J98: Eaux intérieures ; pêche min 1 (25) ; Tirisfal Glades ~15% de moins (poissons malades)
A99: 6291 | B99: Goujon brillant cru | C99: Pêche | D99: Eaux douces (étangs, rivières, lacs) | E99: Capital cities | H99: 15 | I99: Wowhead Classic — Best Fishing Farming Spots (1.15.8) | J99: Eaux intérieures ; pêche min 1 (25) ; Tirisfal Glades ~15% de moins (poissons malades)
A100: 6303 | B100: Maquereau ombré cru | C100: Pêche | D100: Eaux côtières | E100: Durotar | I100: Wowhead Classic — Best Fishing Farming Spots (1.15.8) | J100: Côtier ; pêche min 1 (25) ; recommandé surtout à Durotar
A101: 6303 | B101: Maquereau ombré cru | C101: Pêche | D101: Eaux côtières | E101: Teldrassil | I101: Wowhead Classic — Best Fishing Farming Spots (1.15.8) | J101: Côtier ; pêche min 1 (25) ; recommandé surtout à Durotar
A102: 6289 | B102: Lutjan à longue mâchoire cru | C102: Pêche | D102: Eaux douces | E102: Capital cities | I102: Wowhead Classic — Best Fishing Farming Spots (1.15.8) | J102: Villes capitales = le plus efficace ; aussi zones 1-10 et 20-30 avec un taux plus faible ; pêche min 1 (75)
...

Sheet Marchands
A1: id_PNJ | B1: Marchand | C1: Zone (client FR) | D1: mapID | E1: X (%) | F1: Y (%) | G1: id_ingrédient | H1: Ingrédient
A2: 2134 | B2: Mme Winters | C2: Clairières de Tirisfal | D2: 1420 | E2: 61.1 | F2: 52.7 | G2: 159 | H2: =IFERROR(INDEX(Ingrédients!$B:$B,MATCH(G2,Ingrédients!$A:$A,0)),"—") -> Eau de source
A3: 2134 | B3: Mme Winters | C3: Clairières de Tirisfal | D3: 1420 | E3: 61.1 | F3: 52.7 | G3: 4470 | H3: =IFERROR(INDEX(Ingrédients!$B:$B,MATCH(G3,Ingrédients!$A:$A,0)),"—") -> Bois simple
A4: 2118 | B4: Abigail Shiel | C4: Clairières de Tirisfal | D4: 1420 | E4: 61 | F4: 52.4 | G4: 2678 | H4: =IFERROR(INDEX(Ingrédients!$B:$B,MATCH(G4,Ingrédients!$A:$A,0)),"—") -> Epices douces
A5: 2118 | B5: Abigail Shiel | C5: Clairières de Tirisfal | D5: 1420 | E5: 61 | F5: 52.4 | G5: 4536 | H5: =IFERROR(INDEX(Ingrédients!$B:$B,MATCH(G5,Ingrédients!$A:$A,0)),"—") -> Pomme rouge brillante
A6: 5688 | B6: Renée l'aubergiste | C6: La taverne des Pendus | D6: 1420 | E6: 61.7 | F6: 52.1 | G6: 159 | H6: =IFERROR(INDEX(Ingrédients!$B:$B,MATCH(G6,Ingrédients!$A:$A,0)),"—") -> Eau de source
A7: 6741 | B7: Norman l'aubergiste | C7: Fossoyeuse | D7: 1458 | E7: 67.6 | F7: 38.1 | G7: 159 | H7: =IFERROR(INDEX(Ingrédients!$B:$B,MATCH(G7,Ingrédients!$A:$A,0)),"—") -> Eau de source
A8: 6741 | B8: Norman l'aubergiste | C8: Fossoyeuse | D8: 1458 | E8: 67.6 | F8: 38.1 | G8: 1179 | H8: =IFERROR(INDEX(Ingrédients!$B:$B,MATCH(G8,Ingrédients!$A:$A,0)),"—") -> Lait glacé
A9: 6741 | B9: Norman l'aubergiste | C9: Fossoyeuse | D9: 1458 | E9: 67.6 | F9: 38.1 | G9: 1205 | H9: =IFERROR(INDEX(Ingrédients!$B:$B,MATCH(G9,Ingrédients!$A:$A,0)),"—") -> Jus de melon
A10: 6741 | B10: Norman l'aubergiste | C10: Fossoyeuse | D10: 1458 | E10: 67.6 | F10: 38.1 | G10: 1708 | H10: =IFERROR(INDEX(Ingrédients!$B:$B,MATCH(G10,Ingrédients!$A:$A,0)),"—") -> Nectar sucré
A11: 6741 | B11: Norman l'aubergiste | C11: Fossoyeuse | D11: 1458 | E11: 67.6 | F11: 38.1 | G11: 1645 | H11: =IFERROR(INDEX(Ingrédients!$B:$B,MATCH(G11,Ingrédients!$A:$A,0)),"—") -> Jus de baie lunaire
A12: 6741 | B12: Norman l'aubergiste | C12: Fossoyeuse | D12: 1458 | E12: 67.6 | F12: 38.1 | G12: 8766 | H12: =IFERROR(INDEX(Ingrédients!$B:$B,MATCH(G12,Ingrédients!$A:$A,0)),"—") -> Soupe de rosée matinale
A13: 4555 | B13: Eleanor Rusk | C13: Fossoyeuse | D13: 1458 | E13: 69.1 | F13: 48.5 | G13: 159 | H13: =IFERROR(INDEX(Ingrédients!$B:$B,MATCH(G13,Ingrédients!$A:$A,0)),"—") -> Eau de source
... A30: 4561 | B30: Daniel Bartlett | C30: Fossoyeuse | D30: 1458 | E30: 64.2 | F30: 37.8 | G30: 3713 | H30: =IFERROR(INDEX(Ingrédients!$B:$B,MATCH(G30,Ingrédients!$A:$A,0)),"—") -> Epices apaisantes
A72: Position = celle du joueur pendant l'échange (approximative). Une ligne par marchand et par composant. mapID = identifiant de carte du jeu (plus fiable que le nom de zone, qui dépend de la langue).

Sheet Marchands_recettes
A1: id_PNJ | B1: Marchand | C1: Zone (client FR) | D1: mapID | E1: X (%) | F1: Y (%) | G1: id_objet_recette | H1: Objet vendu | I1: id_recette (onglet Recettes) | J1: Recette cuisinée | K1: Origine
A2: 2118 | B2: Abigail Shiel | C2: Clairières de Tirisfal | D2: 1420 | E2: 61 | F2: 52.4 | G2: 12226 | H2: Recette : Aile de chauve-souris croustillante | I2: 12224 | J2: =IFERROR(INDEX(Recettes!$C:$C,MATCH(I2,Recettes!$A:$A,0)),"—") -> Aile de chauve-souris croustillante | K2: Relevé en jeu (bêta)
A3: 3550 | B3: Martine Tramblay | C3: Clairières de Tirisfal | D3: 1420 | E3: 65.9 | F3: 59.6 | G3: 6325 | H3: Recette : Goujon brillant | I3: 6290 | J3: =IFERROR(INDEX(Recettes!$C:$C,MATCH(I3,Recettes!$A:$A,0)),"—") -> Goujon brillant | K3: Relevé en jeu (bêta)
A4: 3550 | B4: Martine Tramblay | C4: Clairières de Tirisfal | D4: 1420 | E4: 65.9 | F4: 59.6 | G4: 6326 | H4: Recette : Maquereau ombré | I4: 787 | J4: =IFERROR(INDEX(Recettes!$C:$C,MATCH(I4,Recettes!$A:$A,0)),"—") -> Maquereau ombré | K4: Relevé en jeu (bêta)
A5: 3556 | B5: Andrew Hilbert | C5: Forêt des Pins argentés | D5: 1421 | E5: 43.2 | F5: 40.7 | G5: 6892 | H5: Recette : Viande d'ours fumée | I5: 6890 | J5: =IFERROR(INDEX(Recettes!$C:$C,MATCH(I5,Recettes!$A:$A,0)),"—") -> Viande d'ours fumée | K5: Web (QuestieDB, Classic), à confirmer en jeu : id de l'objet recette et position importés de QuestieDB
A6: 2664 | B6: Kelsey Yance | C6: Vallée de Strangleronce | D6: 1434 | E6: 28.2 | F6: 74.3 | G6: 13940 | H6: Recette : Barracuda luisant cuit | I6: 13927 | J6: =IFERROR(INDEX(Recettes!$C:$C,MATCH(I6,Recettes!$A:$A,0)),"—") -> Barracuda luisant cuit | K6: Web (QuestieDB, Classic), à confirmer en jeu : id de l'objet recette et position importés de QuestieDB
A46: Position = celle du joueur pendant l'échange (approximative). Une ligne par recette vendue. Cellules jaune clair = position non relevée.

Sheet Rangs_métier
A1: Rang | B1: Compétence min | C1: Compétence max | D1: Niveau perso requis | E1: Remarque
A2: Apprenti | B2: 1 | C2: 50 | E2: Aucun niveau requis dans la bêta d'après le guide source (apprentissage possible dès la création)
A3: Compagnon | B3: 50 | C3: 150 | D3: 10 | E3: Requiert 50 en Cuisine et niveau 10 (guide source)
A4: Expert | B4: 150 | C4: 225 | E4: Niveau perso requis non récupéré
A5: Artisan | B5: 225 | C5: 300 | E5: Non testé par l'auteur du guide (plafond de niveau de la bêta) ; le jeu compte des recettes jusqu'à 365

Sheet Sources_données
A1: Donnée | B1: Source | C1: URL | D1: Date de consultation
A2: Recettes, composants, niveaux de couleur | B2: SeeMeta — Recettes Cuisine WoW Forever (bêta 1.60.1) | C2: https://seemeta.com/fr/wow-forever/professions/cooking | D2: 2026-10-07
A3: Rangs de métier, niveaux requis | B3: WoW Professions — Cooking Leveling Guide 1-300 | C3: https://www.wow-professions.com/forever/cooking-leveling-guide | D3: 2026-10-07
A4: Smoothies (vendeurs de l'Azeroth Commerce Authority) | B4: Warcraft Tavern — New Cooking Recipes | C4: https://www.warcrafttavern.com/forever/news/new-cooking-recipes-for-world-of-warcraft-forever/ | D4: 2026-10-07
A5: Zones, niveaux et monstres par ingrédient | B5: Wowhead Classic — Best Cooking Ingredient Farming Spots (1.15.8, màj 2024) | C5: https://www.wowhead.com/classic/guide/best-cooking-meat-farming-locations-classic-wow | D5: 2026-10-07
A6: Zones de pêche, compétence requise, taux de prise | B6: Wowhead Classic — Best Fishing Farming Spots (1.15.8, màj 2025) | C6: https://www.wowhead.com/classic/guide/best-fishing-pools-farming-locations-classic-wow | D6: 2026-10-07
A7: Furie du loch crue (Loch Modan) | B7: Warcraft Wiki — Fishing items | C7: https://warcraft.wiki.gg/wiki/Fishing_items | D7: 2026-10-07
A8: Marchands de composants (relevés en jeu) | B8: Addon CuisineMarchands, test dans les Clairières de Tirisfal (bêta) | C8: Fichier SavedVariables CuisineMarchands.lua | D8: 2026-10-07
A9: Épices vendues par les marchands de cuisine | B9: Warcraft Tavern — Cooking guide Forever | C9: https://www.warcrafttavern.com/forever/guides/cooking/ | D9: 2026-10-07
A10: Marchands et recettes vendues (Classic, à confirmer en jeu) | B10: Warcraft Wiki — pages des PNJ et listes de recettes de cuisine | C10: https://warcraft.wiki.gg/wiki/List_of_Apprentice_Cooking_Recipes | D10: 2026-10-08
A11: Maîtres de cuisine et coordonnées | B11: Overgear et Icy Veins — guides de cuisine WoW Classic | C11: https://overgear.com/guides/wow-classic/cooking/ | D11: 2026-10-08
A12: Maîtres, quêtes, vendeurs de recettes, niveaux orange, butin des nouveaux ingrédients | B12: QuestieDB (github.com/Questie/QuestieDB), données Classic Era reprojetées sur Forever - licence GPL v3 à confirmer | C12: https://github.com/Questie/QuestieDB | D12: 2026-10-10
A13: Recettes, composants et paliers (recoupement) | B13: AtlasLoot Classic (github.com/Hoizame/AtlasLootClassic), GPL v2 | C13: https://github.com/Hoizame/AtlasLootClassic | D13: 2026-10-10

Sheet Web_marchands
A1: PNJ (EN) | B1: id_PNJ (Forever) | C1: Zone | D1: Position (x / y) | E1: Faction | F1: Article | G1: Type | H1: Prix (source) | I1: Source (URL) | J1: Période indiquée par la source | K1: Relevé en jeu (Forever) | L1: Remarque
A2: Abigail Shiel | B2: 2118 | C2: Brill, Clairières de Tirisfal | D2: 61 / 52 | E2: Horde | F2: Mild Spices (épices douces) | G2: composant | H2: 10c (x5) | I2: https://warcraft.wiki.gg/wiki/Abigail_Shiel | J2: Actuel | K2: Oui | L2: Confirmé en jeu (61 / 52,4)
A3: Abigail Shiel | B3: 2118 | C3: Brill, Clairières de Tirisfal | D3: 61 / 52 | E3: Horde | F3: Simple Flour (farine simple) | G3: composant | H3: 25c (x5) | I3: https://warcraft.wiki.gg/wiki/Abigail_Shiel | J3: Ajouté au patch 2.0.3 | K3: Non | L3: Absent du relevé en jeu : cohérent avec un client sans le contenu de 2.0.3
A4: Abigail Shiel | B4: 2118 | C4: Brill, Clairières de Tirisfal | D4: 61 / 52 | E4: Horde | F4: Recipe: Crispy Bat Wing | G4: recette | H4: 25c | I4: https://warcraft.wiki.gg/wiki/Abigail_Shiel | J4: Classic | K4: Oui | L4: Recette de la quête 1 (objet 12226)
A5: Andrew Hilbert | C5: Sepulcher, Silverpine Forest | D5: 43 / 41 | E5: Horde | F5: Hot Spices (épices fortes) | G5: composant | H5: 40c | I5: https://warcraft.wiki.gg/wiki/Andrew_Hilbert | J5: Classic (retiré en 3.1.0) | K5: Non | L5: À relever en jeu
A6: Andrew Hilbert | C6: Sepulcher, Silverpine Forest | D6: 43 / 41 | E6: Horde | F6: Mild Spices (épices douces) | G6: composant | H6: 10c (x5) | I6: https://warcraft.wiki.gg/wiki/Andrew_Hilbert | J6: Actuel | K6: Non | L6: À relever en jeu
A7: Andrew Hilbert | C7: Sepulcher, Silverpine Forest | D7: 43 / 41 | E7: Horde | F7: Salt (sel) | G7: composant | H7: 50c | I7: https://warcraft.wiki.gg/wiki/Andrew_Hilbert | J7: Actuel | K7: Non | L7: À relever en jeu
A8: Andrew Hilbert | C8: Sepulcher, Silverpine Forest | D8: 43 / 41 | E8: Horde | F8: Recipe: Smoked Bear Meat | G8: recette | H8: 2s 50c | I8: https://warcraft.wiki.gg/wiki/Andrew_Hilbert | J8: Classic | K8: Non | L8: Recette de la quête 2 : à acheter ici (côté Horde)
A9: Daniel Bartlett | B9: 4561 | C9: Trade Quarter, Undercity (Fossoyeuse) | D9: non indiquée | E9: Horde | F9: Hot Spices (épices fortes) | G9: composant | H9: 40c | I9: https://warcraft.wiki.gg/wiki/Daniel_Bartlett | J9: Classic (retiré en 3.1.0) | K9: Oui | L9: Confirmé en jeu (64,2 / 37,8)
A10: Daniel Bartlett | B10: 4561 | C10: Trade Quarter, Undercity (Fossoyeuse) | D10: non indiquée | E10: Horde | F10: Soothing Spices (épices apaisantes) | G10: composant | H10: 1s 60c | I10: https://warcraft.wiki.gg/wiki/Daniel_Bartlett | J10: Classic (retiré en 3.1.0) | K10: Oui | L10: Confirmé en jeu
A11: Felicia Doan | B11: 4775 | C11: Trade Quarter, Undercity (Fossoyeuse) | D11: non indiquée | E11: Horde | F11: Hot Spices (épices fortes) | G11: composant | H11: 34c (prix de la page) | I11: https://warcraft.wiki.gg/wiki/Felicia_Doan | J11: Classic (retiré en 3.1.0) | K11: Oui | L11: Confirmé en jeu (64,1 / 50,2)
A12: Felicia Doan | B12: 4775 | C12: Trade Quarter, Undercity (Fossoyeuse) | D12: non indiquée | E12: Horde | F12: Soothing Spices (épices apaisantes) | G12: composant | H12: 1s 36c (prix de la page) | I12: https://warcraft.wiki.gg/wiki/Felicia_Doan | J12: Classic (retiré en 3.1.0) | K12: Oui | L12: Confirmé en jeu
A13: Ronald Burch | B13: 4553 | C13: Trade Quarter, Undercity (Fossoyeuse) | D13: non indiquée | E13: Horde | F13: Hot Spices (épices fortes) | G13: composant | H13: 40c | I13: https://warcraft.wiki.gg/wiki/Ronald_Burch | J13: Classic (retiré en 3.1.0) | K13: Non | L13: Marchand de cuisine à visiter : à relever en jeu
A14: Ronald Burch | B14: 4553 | C14: Trade Quarter, Undercity (Fossoyeuse) | D14: non indiquée | E14: Horde | F14: Soothing Spices (épices apaisantes) | G14: composant | H14: 1s 60c | I14: https://warcraft.wiki.gg/wiki/Ronald_Burch | J14: Classic (retiré en 3.1.0) | K14: Non | L14: À relever en jeu
A15: Ronald Burch | B15: 4553 | C15: Trade Quarter, Undercity (Fossoyeuse) | D15: non indiquée | E15: Horde | F15: Mild Spices, Simple Flour, Refreshing Spring Water | G15: composant | H15: 10c / 25c / 5c (x5) | I15: https://warcraft.wiki.gg/wiki/Ronald_Burch | J15: Actuel | K15: Non | L15: Liste de la version actuelle du jeu : à confirmer
A16: Eleanor Rusk | B16: 4555 | C16: Trade Quarter, Undercity (Fossoyeuse) | D16: non indiquée | E16: Horde | F16: Refreshing Spring Water, Ice Cold Milk, Melon Juice, Sweet Nectar, Moonberry Juice, Morning Glory Dew | G16: composant | H16: 5c / 1s25c / 5s / 10s / 20s / 40s (x5) | I16: https://warcraft.wiki.gg/wiki/Eleanor_Rusk | J16: Classic | K16: Oui | L16: Confirmé en jeu (69,1 / 48,5)
A17: Eleanor Rusk | B17: 4555 | C17: Trade Quarter, Undercity (Fossoyeuse) | D17: non indiquée | E17: Horde | F17: Simple Wood (bois simple) | G17: composant | H17: 38c | I17: https://warcraft.wiki.gg/wiki/Eleanor_Rusk | J17: Classic | K17: Oui | L17: Confirmé en jeu
A18: Eleanor Rusk | B18: 4555 | C18: Trade Quarter, Undercity (Fossoyeuse) | D18: non indiquée | E18: Horde | F18: Star Wood (bois d'étoile) | G18: composant | H18: non listé | I18: https://warcraft.wiki.gg/wiki/Eleanor_Rusk | J18: Absent de la page | K18: Oui | L18: Écart : vendu en jeu, absent de la page
A19: Thaddeus Webb | B19: 4617 | C19: Apothecarium, Undercity (Fossoyeuse) | D19: non indiquée | E19: Horde | F19: Simple Wood (bois simple), Star Wood (bois d'étoile) | G19: composant | H19: 38c / 45s | I19: https://warcraft.wiki.gg/wiki/Thaddeus_Webb | J19: Actuel (liste Classic contradictoire) | K19: Oui | L19: Confirmé en jeu (62 / 60,9)
A20: Chef Audrey | C20: Fossoyeuse | D20: 63 / 34,4 | E20: Horde | F20: Refreshing Spring Water, Ice Cold Milk, Melon Juice, Sweet Nectar, Moonberry Juice, Morning Glory Dew (+ champignons) | G20: composant | H20: 5c / 1s25c / 5s / 10s / 20s / 40s (x5) | I20: https://warcraft.wiki.gg/wiki/Chef_Audrey | J20: Actuel | K20: Non | L20: À relever en jeu : distinct de Norman l'aubergiste (67,6 / 38,1)
A21: Martine Tramblay | B21: 3550 | C21: Death's Watch Waystation, Clairières de Tirisfal | D21: 66 / 60 | E21: Horde | F21: Recipe: Brilliant Smallfish | G21: recette | H21: 40c | I21: https://warcraft.wiki.gg/wiki/Martine_Tramblay | J21: Non daté | K21: Oui | L21: Confirmé en jeu (65,9 / 59,6), objet 6325
A22: Martine Tramblay | B22: 3550 | C22: Death's Watch Waystation, Clairières de Tirisfal | D22: 66 / 60 | E22: Horde | F22: Recipe: Slitherskin Mackerel | G22: recette | H22: 40c | I22: https://warcraft.wiki.gg/wiki/Martine_Tramblay | J22: Non daté | K22: Oui | L22: Confirmé en jeu, objet 6326
A23: Martine Tramblay | B23: 3550 | C23: Death's Watch Waystation, Clairières de Tirisfal | D23: 66 / 60 | E23: Horde | F23: Couteau de chef (objet 273636) | G23: autre | H23: non listé | I23: https://warcraft.wiki.gg/wiki/Martine_Tramblay | J23: Absent de la page | K23: Oui | L23: Objet propre à Forever : absent des sources web
A24: Xen'to | B24: 3400 | C24: Orgrimmar | D24: non indiquée | E24: Horde | F24: Water, Mild/Hot/Soothing Spices, Simple Flour, Recipe: Smoked Sagefish, Recipe: Sagefish Delight | G24: composant + recette | H24: 10c à 50s | I24: https://wowclassicdb.com/wotlk/npc/3400 | J24: Version WotLK de la base | K24: Non | L24: À relever en jeu
A25: Wulan | C25: Shadowprey Village, Désolace | D25: 26 / 70 | E25: Horde | F25: Expert Cookbook (livre de cuisine de l'expert) | G25: recette | H25: 1g | I25: https://warcraft.wiki.gg/wiki/Wulan | J25: Classic (retiré en 3.1.0) | K25: Non | L25: Livre pour passer au rang Expert
A26: Wulan | C26: Shadowprey Village, Désolace | D26: 26 / 70 | E26: Horde | F26: Hot Spices, Soothing Spices | G26: composant | H26: 40c / 1s 60c | I26: https://warcraft.wiki.gg/wiki/Wulan | J26: Classic (retiré en 3.1.0) | K26: Non | L26: À relever en jeu

Sheet Web_recettes
A1: Recette (EN) | B1: Niveau d'apprentissage | C1: Marchand | D1: Zone | E1: Position | F1: Faction | G1: Prix | H1: Source (URL)
A2: Brilliant Smallfish | B2: 1 | C2: Martine Tramblay | D2: Clairières de Tirisfal | E2: 66 / 60 | F2: Horde | G2: 40c | H2: https://warcraft.wiki.gg/wiki/Martine_Tramblay
A3: Slitherskin Mackerel | B3: 1 | C3: Martine Tramblay | D3: Clairières de Tirisfal | E3: 66 / 60 | F3: Horde | G3: 40c | H3: https://warcraft.wiki.gg/wiki/Martine_Tramblay
A4: Scorpid Surprise | B4: 20 | C4: Grimtak | D4: Razor Hill, Durotar | E4: non indiquée | F4: Horde | G4: 1s 33c | H4: https://warcraft.wiki.gg/wiki/List_of_Apprentice_Cooking_Recipes
A5: Roasted Kodo Meat | B5: 35 | C5: Wunna Darkmane | D5: Bloodhoof Village, Mulgore | E5: non indiquée | F5: Horde | G5: 2s 28c | H5: https://warcraft.wiki.gg/wiki/List_of_Apprentice_Cooking_Recipes
A6: Bat Bites | B6: 50 | C6: Master Chef Mouldier | D6: Tranquillien, Ghostlands | E6: non indiquée | F6: Horde | G6: 4s | H6: https://warcraft.wiki.gg/wiki/List_of_Apprentice_Cooking_Recipes
A7: Strider Stew | B7: 50 | C7: Tari'qa | D7: Crossroads, Northern Barrens | E7: 51,6 / 30 | F7: Horde | G7: 4s 40c | H7: https://warcraft.wiki.gg/wiki/List_of_Apprentice_Cooking_Recipes
A8: Crunchy Spider Surprise | B8: 60 | C8: Master Chef Mouldier | D8: Tranquillien, Ghostlands | E8: non indiquée | F8: Horde | G8: 4s | H8: https://warcraft.wiki.gg/wiki/List_of_Apprentice_Cooking_Recipes
A9: Crispy Lizard Tail | B9: 100 | C9: Tari'qa | D9: Crossroads, Northern Barrens | E9: 51,6 / 30 | F9: Horde | G9: 4s | H9: https://warcraft.wiki.gg/wiki/List_of_Journeyman_Cooking_Recipes
A10: Lean Wolf Steak | B10: 125 | C10: Zargh | D10: Crossroads, Northern Barrens | E10: 52,6 / 29,8 | F10: Horde | G10: 16s | H10: https://warcraft.wiki.gg/wiki/List_of_Journeyman_Cooking_Recipes
A11: Hot Lion Chops | B11: 125 | C11: Zargh | D11: Crossroads, Northern Barrens | E11: 52,6 / 29,8 | F11: Horde | G11: 18s | H11: https://warcraft.wiki.gg/wiki/List_of_Journeyman_Cooking_Recipes
A12: Curiously Tasty Omelet | B12: 130 | C12: Keena | D12: Hammerfall, Arathi Highlands | E12: 74 / 32,6 | F12: Horde | G12: 16s | H12: https://warcraft.wiki.gg/wiki/List_of_Journeyman_Cooking_Recipes
... A29: Expert Cookbook (rang Expert) | B29: 125 | C29: Wulan | D29: Shadowprey Village, Désolace | E29: 26 / 70 | F29: Horde | G29: 1g | H29: https://warcraft.wiki.gg/wiki/Wulan

Sheet Web_maitres
A1: Maître de cuisine | B1: Zone | C1: Position | D1: Faction | E1: Source (URL)
A2: Eunice Burch | B2: Fossoyeuse | C2: 62 / 44 | D2: Horde | E2: https://overgear.com/guides/wow-classic/cooking/
A3: Aska Mistrunner | B3: Pitons-du-Tonnerre | C3: 51 / 52 | D3: Horde | E3: https://overgear.com/guides/wow-classic/cooking/
A4: Zamja | B4: Orgrimmar | C4: 57 / 53 | D4: Horde | E4: https://overgear.com/guides/wow-classic/cooking/
A5: Pyall Silentstride | B5: Mulgore | C5: 45 / 57 | D5: Horde | E5: https://overgear.com/guides/wow-classic/cooking/
A6: Mudduk | B6: Stranglethorn Vale | C6: 37 / 49 | D6: Horde | E6: https://overgear.com/guides/wow-classic/cooking/
A7: Duhng | B7: Tarides | C7: non indiquée | D7: Horde | E7: https://www.icy-veins.com/wow-classic/classic-cooking-profession-guide

Sheet QDB_Maitres
A1: ID PNJ | B1: Maître (FR) | C1: Titre (FR) | D1: Titre (EN) | E1: Zone | F1: Coordonnées | G1: Faction | H1: Niveau
A2: 5482 | B2: Stephen Ryback | C2: Maître des cuisiniers | D2: Cooking Trainer | E2: Cité de Stormwind | F2: 78.2, 53.1 | G2: Alliance | H2: 35
A3: 4210 | B3: Alegorn | C3: Maître des cuisiniers | D3: Cooking Trainer | E3: Darnassus | F3: 49.0, 21.2 | G3: Alliance | H3: 35
A4: 1355 | B4: Cuisinier Ghilm | C4: Maître des cuisiniers | D4: Cooking Trainer | E4: Dun Morogh | F4: 68.4, 54.5 | G4: Alliance | H4: 9
A5: 1699 | B5: Gremlock Pilsnor | C5: Maître des cuisiniers | D5: Cooking Trainer | E5: Dun Morogh | F5: 47.7, 52.3 | G5: Alliance | H5: 10
A6: 1430 | B6: Tomas | C6: Cuisinier | D6: Cook | E6: Forêt d'Elwynn | F6: 44.4, 66.0 | G6: Alliance | H6: 10
A7: 5159 | B7: Daryl Riknussun | C7: Maître des cuisiniers | D7: Cooking Trainer | E7: Ironforge | F7: 60.1, 36.4 | G7: Alliance | H7: 35
A8: 3087 | B8: Crystal Boughman | C8: Maître des cuisiniers | D8: Cooking Trainer | E8: Les Carmines | F8: 17.7, 43.5 | G8: Alliance | H8: 22
A9: 6286 | B9: Zarrin | C9: Cuisinier | D9: Cook | E9: Teldrassil | F9: 57.1, 61.3 | G9: Alliance | H9: 13
A10: 8306 | B10: Duhng | C10: Cuisinier | D10: Cook | E10: Les Tarides | F10: 55.3, 31.8 | G10: Horde | H10: 18
A11: 3067 | B11: Pyall Silentstride | C11: Cuisinier | D11: Cook | E11: Mulgore | F11: 44.9, 61.7 | G11: Horde | H11: 12
A12: 3399 | B12: Zamja | C12: Maître des cuisiniers | D12: Cooking Trainer | E12: Orgrimmar | F12: 57.4, 54.0 | G12: Horde | H12: 35
A13: 3026 | B13: Aska Mistrunner | C13: Maître des cuisiniers | D13: Cooking Trainer | E13: Thunder Bluff | F13: 50.7, 53.1 | G13: Horde | H13: 45
... A15: 1382 | B15: Mudduk | C15: Excellent cuisinier | D15: Superior Cook | E15: Vallée de Strangleronce | F15: 31.3, 28.0 | G15: Horde | H15: 40

Sheet QDB_Quetes
A1: ID quête | B1: Quête (FR) | C1: Quête (EN) | D1: Niveau quête | E1: Niveau requis | F1: Cuisine requise | G1: Pourquoi elle est listée | H1: Objets demandés | I1: Recette en récompense | J1: Donneur (FR) | K1: Zone du donneur | L1: Coordonnées | M1: Faction
A2: 619 | B2: Allécher Negolash | C2: Enticing Negolash | D2: 52 | E2: 1 | G2: Demande des plats/composants | H2: Aile de busard grillée; Vin de Junglevine | M2: Les deux
A3: 8529 | B3: L'Alliance a besoin de plus de jaune-queue tacheté ! | C3: The Alliance Needs More Spotted Yellowtail! | D3: 60 | E3: 1 | G3: Demande des plats/composants | H3: Jaune-queue tacheté | J3: Chasseresse Swiftriver | K3: Ironforge | L3: 71.5, 69.1 | M3: Les deux
A4: 8527 | B4: L'Alliance a besoin de plus de rôti de raptor ! | C4: The Alliance Needs More Roast Raptor! | D4: 60 | E4: 1 | G4: Demande des plats/composants | H4: Rôti de raptor | J4: Sarah Sadwhistle | K4: Ironforge | L4: 71.3, 70.3 | M4: Les deux
A5: 8525 | B5: L'Alliance a besoin de plus de thon arc-en-ciel ! | C5: The Alliance Needs More Rainbow Fin Albacore! | D5: 60 | E5: 1 | G5: Demande des plats/composants | H5: Thon arc-en-ciel | J5: Khirry le Gastronome | K5: Ironforge | L5: 71.0, 69.9 | M5: Les deux
A6: 8614 | B6: La Horde a besoin de plus de jaunes-queues tachetés ! | C6: The Horde Needs More Spotted Yellowtail! | D6: 60 | E6: 1 | G6: Demande des plats/composants | H6: Jaune-queue tacheté | J6: Pêcheur Lin'do | K6: Orgrimmar | L6: 29.1, 68.9 | M6: Les deux
A7: 8616 | B7: La Horde a besoin de plus de pains de saumon ! | C7: The Horde Needs More Baked Salmon! | D7: 60 | E7: 1 | G7: Demande des plats/composants | H7: Pain de saumon | J7: Chef Sharpclaw | K7: Orgrimmar | L7: 28.8, 68.4 | M7: Les deux
A8: 8612 | B8: La Horde a besoin de plus de steaks de loup ! | C8: The Horde Needs More Lean Wolf Steaks! | D8: 60 | E8: 1 | G8: Demande des plats/composants | H8: Steak de loup | J8: Garde de sang Rawtar | K8: Orgrimmar | L8: 28.8, 67.4 | M8: Les deux
A9: 16 | B9: Procurer de l'eau à Gerard | C9: Give Gerard a Drink | D9: 1 | E9: 1 | G9: Demande des plats/composants | H9: Eau de source | J9: Gerard Tiller | K9: Forêt d'Elwynn | L9: 43.1, 85.5 | M9: Alliance
A10: 4161 | B10: Une recette kaldorei | C10: Recipe of the Kaldorei | D10: 7 | E10: 1 | F10: 1 | G10: Compétence cuisine requise / Donne une recette / Demande des plats/composants | H10: Petite patte d'araignée | I10: Recette : Kébab d'araignée kaldorei | J10: Zarrin | K10: Teldrassil | L10: 57.1, 61.3 | M10: Alliance
A11: 317 | B11: Ravitailler le Crache-vapeur | C11: Stocking Jetsteam | D11: 6 | E11: 2 | G11: Demande des plats/composants | H11: Morceau de viande de sanglier; Fourrure d'ours épaisse | J11: Pilote Bellowfiz | K11: Dun Morogh | L11: 49.4, 48.4 | M11: Alliance
A12: 384 | B12: Côtes de sanglier à la bière | C12: Beer Basted Boar Ribs | D12: 7 | E12: 5 | G12: Donne une recette / Demande des plats/composants | H12: Côtes de sanglier des rochers; Bière au malt Rhapsody | I12: Recette : Côtes de sanglier à la bière | J12: Ragnar Thunderbrew | K12: Dun Morogh | L12: 46.8, 52.4 | M12: Alliance
A13: 86 | B13: Une tourte pour Billy | C13: Pie for Billy | D13: 6 | E13: 5 | G13: Demande des plats/composants | H13: Morceau de viande de sanglier | J13: Billy Maclure | K13: Forêt d'Elwynn | L13: 43.1, 85.7 | M13: Alliance
A14: 418 | B14: Les boudins de Thelsamar | C14: Thelsamar Blood Sausages | D14: 11 | E14: 7 | G14: Donne une recette / Demande des plats/composants | H14: Tripes de sanglier; Viande d'ours; Ichor d'araignée | I14: Recette : Boudin | J14: Vidra Hearthstove | K14: Loch Modan | L14: 34.8, 49.3 | M14: Alliance
A15: 2178 | B15: Brouet de trotteur | C15: Easy Strider Living | D15: 12 | E15: 9 | F15: 10 | G15: Compétence cuisine requise / Donne une recette / Demande des plats/composants | H15: Viande de trotteur | I15: Recette : Brouet de trotteur | J15: Alanndarian Nightsong | K15: Sombrivage | L15: 37.7, 40.7 | M15: Alliance
A16: 22 | B16: La tourte au foie de Broche-tripes | C16: Goretusk Liver Pie | D16: 12 | E16: 9 | G16: Donne une recette / Demande des plats/composants | H16: Foie de Broche-tripes | I16: Recette : Tourte au foie de Broche-tripes | J16: Salma Saldean | K16: Marche de l'Ouest | L16: 56.4, 30.5 | M16: Alliance
A17: 38 | B17: Le ragoût de la marche de l'Ouest | C17: Westfall Stew | D17: 13 | E17: 9 | G17: Donne une recette / Demande des plats/composants | H17: Viande filandreuse de vautour; Oeil de murloc; Groin de Broche-tripes; Okra | I17: Recette : Ragoût de la marche de l'Ouest | J17: Salma Saldean | K17: Marche de l'Ouest | L17: 56.4, 30.5 | M17: Alliance
A18: 385 | B18: Chasse aux crocilisques | C18: Crocolisk Hunting | D18: 15 | E18: 10 | G18: Donne une recette / Demande des plats/composants | H18: Viande de crocilisque; Peau de crocilisque | I18: Recette : Steak de crocilisque | J18: Marek Ironheart | K18: Loch Modan | L18: 81.8, 61.7 | M18: Alliance
A19: 6962 | B19: Des friandises pour Grand-père Hiver | C19: Treats for Great-father Winter | D19: 60 | E19: 10 | G19: Demande des plats/composants | H19: Biscuit de pain d'épice; Lait glacé | J19: Grand-père Hiver | K19: Orgrimmar | L19: 52.5, 69.2 | M19: Horde
A20: 7025 | B20: Des friandises pour Grandpère Hiver | C20: Treats for Greatfather Winter | D20: 60 | E20: 10 | G20: Demande des plats/composants | H20: Biscuit de pain d'épice; Lait glacé | J20: Grandpère Hiver | K20: Ironforge | L20: 33.2, 65.4 | M20: Alliance
A21: 862 | B21: Brouet de rat | C21: Dig Rat Stew | D21: 23 | E21: 15 | F21: 1 | G21: Compétence cuisine requise / Donne une recette / Demande des plats/composants | H21: Rat fouisseur | I21: Recette : Brouet de rat | J21: Boustiff' | K21: Les Tarides | L21: 55.3, 31.8 | M21: Horde
A22: 92 | B22: Goulash des Carmines | C22: Redridge Goulash | D22: 18 | E22: 15 | G22: Donne une recette / Demande des plats/composants | H22: Groin de grand Broche-tripes; Viande de condor coriace; Chair croustillante d'araignée | I22: Recette : Goulash des Carmines | J22: Chef Breanna | K22: Les Carmines | L22: 17.6, 43.8 | M22: Alliance
A23: 127 | B23: Criée aux poissons | C23: Selling Fish | D23: 21 | E23: 16 | G23: Donne une recette | H23: Poisson-lune | I23: Recette : Soupe aux ailerons de murloc | J23: Chef des docks Baren | K23: Les Carmines | L23: 22.6, 47.4 | M23: Alliance
A24: 93 | B24: Gâteaux au crabe brun | C24: Dusky Crab Cakes | D24: 20 | E24: 17 | G24: Donne une recette / Demande des plats/composants | H24: Patte d'araignée fondante | I24: Recette : Tourte d'araignée fondante | J24: Chef Grual | K24: Bois de la Pénombre | L24: 73.8, 43.5 | M24: Alliance
A25: 498 | B25: Sauvetage | C25: The Rescue | D25: 22 | E25: 17 | G25: Donne une recette | I25: Recette : Steak de grand ours | J25: Krusk | K25: Contreforts d'Hillsbrad | L25: 63.2, 20.7 | M25: Horde
A26: 90 | B26: Kébab de loup assaisonné | C26: Seasoned Wolf Kabobs | D26: 25 | E26: 18 | G26: Donne une recette / Demande des plats/composants | H26: Steak de loup; Herbes aromatiques de Stormwind | I26: Recette : Kébab de loup assaisonné | J26: Chef Grual | K26: Bois de la Pénombre | L26: 73.8, 43.5 | M26: Alliance
A27: 471 | B27: Les devoirs de l'apprenti | C27: Apprentice's Duties | D27: 26 | E27: 18 | G27: Donne une recette | H27: Peau de crocilisque géant | I27: Recette : Gombo de crocilisque | J27: James Halloran | K27: Les Paluns | L27: 8.6, 55.7 | M27: Alliance
A28: 8615 | B28: La Horde a besoin de pains de saumon ! | C28: The Horde Needs Baked Salmon! | D28: 60 | E28: 20 | G28: Demande des plats/composants | H28: Pain de saumon | J28: Chef Sharpclaw | K28: Orgrimmar | L28: 28.8, 68.4 | M28: Les deux
A29: 150 | B29: Les braconniers murlocs | C29: Murloc Poachers | D29: 20 | E29: 20 | G29: Demande des plats/composants | H29: Aileron de murloc | J29: Chef des docks Baren | K29: Les Carmines | L29: 22.6, 47.4 | M29: Alliance
A30: 501 | B30: L'élixir de douleur | C30: Elixir of Pain | D30: 24 | E30: 21 | G30: Donne une recette | H30: Sang de lion des montagnes | I30: Recette : Côtelettes de lion épicées | J30: Apothicaire Lydon | K30: Contreforts d'Hillsbrad | L30: 61.4, 19.1 | M30: Horde
A31: 296 | B31: La vengeance d'Ormer | C31: Ormer's Revenge | D31: 29 | E31: 22 | G31: Donne une recette | H31: Serre de Grondecroc | I31: Recette : Omelette au goût étrange | J31: Ormer Ironbraid | K31: Les Paluns | L31: 38.2, 50.9 | M31: Alliance
A32: 555 | B32: Bisque de tortue apaisante | C32: Soothing Turtle Bisque | D32: 31 | E32: 28 | G32: Donne une recette / Demande des plats/composants | H32: Viande de tortue; Epices apaisantes | I32: Recette : Bisque de tortue apaisante | J32: Chef Jessen | K32: Contreforts d'Hillsbrad | L32: 51.9, 58.7 | M32: Alliance
A33: 7321 | B33: Bisque de tortue apaisante | C33: Soothing Turtle Bisque | D33: 31 | E33: 28 | F33: 1 | G33: Compétence cuisine requise / Donne une recette / Demande des plats/composants | H33: Viande de tortue; Epices apaisantes | I33: Recette : Bisque de tortue apaisante | J33: Christoph Jeffcoat | K33: Contreforts d'Hillsbrad | L33: 62.3, 19.0 | M33: Horde
A34: 1218 | B34: Epices apaisantes | C34: Soothing Spices | D34: 35 | E34: 30 | G34: Demande des plats/composants | H34: Epices apaisantes | J34: Jarl "Oeil-des-marais" | K34: Marécage d'Âprefange | L34: 55.4, 26.3 | M34: Les deux
A35: 564 | B35: Un problème très coûteux | C35: Costly Menace | D35: 34 | E35: 30 | G35: Donne une recette | I35: Recette : Délicieux steak de lion | J35: Darren Malvew | K35: Contreforts d'Hillsbrad | L35: 52.4, 56.0 | M35: Alliance
A36: 703 | B36: Ailes de busard grillées | C36: Barbecued Buzzard Wings | D36: 40 | E36: 33 | G36: Donne une recette / Demande des plats/composants | H36: Aile de busard | I36: Recette : Aile de busard grillée | J36: Rigglefuzz | K36: Terres ingrates | L36: 42.4, 52.9 | M36: Les deux
A37: 8526 | B37: L'Alliance a besoin de rôtis de raptor ! | C37: The Alliance Needs Roast Raptor! | D37: 60 | E37: 33 | G37: Demande des plats/composants | H37: Rôti de raptor | J37: Sarah Sadwhistle | K37: Ironforge | L37: 71.3, 70.3 | M37: Les deux
A38: 6612 | B38: Je connais un gars... | C38: I Know A Guy... | D38: 45 | E38: 35 | F38: 225 | G38: Compétence cuisine requise | J38: Daryl Riknussun | K38: Ironforge | L38: 60.1, 36.4 | M38: Alliance
A39: 6610 | B39: Surprise de palourdes | C39: Clamlette Surprise | D39: 45 | E39: 35 | F39: 225 | G39: Compétence cuisine requise / Demande des plats/composants | H39: Oeuf géant; Chair de palourde piquante; Emmental d'Alterac | J39: Dirge Quikcleave | K39: Tanaris | L39: 52.6, 28.1 | M39: Les deux
A40: 6611 | B40: Vers Gadgetzan vous allez ! | C40: To Gadgetzan You Go! | D40: 45 | E40: 35 | F40: 225 | G40: Compétence cuisine requise | J40: Zamja | K40: Orgrimmar | L40: 57.4, 54.0 | M40: Horde
A41: 8799 | B41: Le héros du jour | C41: The Hero of the Day | D41: 60 | E41: 40 | F41: 300 | G41: Compétence cuisine requise / Demande des plats/composants | H41: Sel de Fonderoc | J41: Kaymard Copperpinch | K41: Orgrimmar | L41: 53.3, 66.5 | M41: Horde
A42: 8763 | B42: Le héros du jour | C42: The Hero of the Day | D42: 60 | E42: 40 | F42: 300 | G42: Compétence cuisine requise / Demande des plats/composants | H42: Sel de Fonderoc | J42: Wulmort Jinglepocket | K42: Ironforge | L42: 33.7, 67.2 | M42: Alliance
A43: 8528 | B43: L'Alliance a besoin de jaune-queue tacheté ! | C43: The Alliance Needs Spotted Yellowtail! | D43: 60 | E43: 42 | G43: Demande des plats/composants | H43: Jaune-queue tacheté | J43: Chasseresse Swiftriver | K43: Ironforge | L43: 71.5, 69.1 | M43: Les deux
A44: 8611 | B44: La Horde a besoin de steaks de loup ! | C44: The Horde Needs Lean Wolf Steaks! | D44: 60 | E44: 49 | G44: Demande des plats/composants | H44: Steak de loup | J44: Garde de sang Rawtar | K44: Orgrimmar | L44: 28.8, 67.4 | M44: Les deux
A45: 8613 | B45: La Horde a besoin de jaunes-queues tachetés ! | C45: The Horde Needs Spotted Yellowtail! | D45: 60 | E45: 52 | G45: Demande des plats/composants | H45: Jaune-queue tacheté | J45: Pêcheur Lin'do | K45: Orgrimmar | L45: 29.1, 68.9 | M45: Les deux
A46: 8524 | B46: L'Alliance a besoin de thon arc-en-ciel ! | C46: The Alliance Needs Rainbow Fin Albacore! | D46: 60 | E46: 54 | G46: Demande des plats/composants | H46: Thon arc-en-ciel | J46: Khirry le Gastronome | K46: Ironforge | L46: 71.0, 69.9 | M46: Les deux
A47: 8313 | B47: Partager la connaissance | C47: Sharing the Knowledge | D47: 57 | E47: 54 | F47: 285 | G47: Compétence cuisine requise | M47: Les deux
A48: 8307 | B48: Recette du désert | C48: Desert Recipe | D48: 57 | E48: 54 | F48: 285 | G48: Compétence cuisine requise | J48: Calandrath | K48: Silithus | L48: 51.9, 39.2 | M48: Les deux
A49: 8317 | B49: Un coup de main à la cuisine | C49: Kitchen Assistance | D49: 57 | E49: 54 | F49: 285 | G49: Compétence cuisine requise / Demande des plats/composants | H49: Boulettes fumées du désert | J49: Calandrath | K49: Silithus | L49: 51.9, 39.2 | M49: Les deux
A50: 8804 | B50: Survivre dans le désert | C50: Desert Survival Kits | D50: 60 | E50: 55 | G50: Demande des plats/composants | H50: Globe d'eau; Anti-venin puissant; Boulettes fumées du désert | M50: Horde
A51: 8585 | B51: L'île de l'effroi ! | C51: The Isle of Dread! | D51: 60 | E51: 60 | G51: Demande des plats/composants | H51: Carcasse de Lakmaeran; Filet de chimaerok | J51: Dirge Quikcleave | K51: Tanaris | L51: 52.6, 28.1 | M51: Les deux
A52: 8778 | B52: La brigade d'Ironforge a besoin d'explosifs ! | C52: The Ironforge Brigade Needs Explosives! | D52: 60 | E52: 60 | G52: Demande des plats/composants | H52: Huile d'immolation; Carburant de fusée des gobelins; Poudre d'explosion dense | M52: Alliance
A53: 8586 | B53: Pyro-côtelettes de chimaerok à la Dirge | C53: Dirge's Kickin' Chimaerok Chops | D53: 60 | E53: 60 | G53: Donne une recette / Demande des plats/composants | H53: Carburant de fusée des gobelins; Sel de Fonderoc | I53: Recette : Pyro-côtelettes de chimaerok à la Dirge | J53: Dirge Quikcleave | K53: Tanaris | L53: 52.6, 28.1 | M53: Les deux
A54: 8856 | B54: Survivre dans le désert | C54: Desert Survival Kits | D54: 0 | E54: 60 | G54: Demande des plats/composants | H54: Globe d'eau; Anti-venin puissant; Boulettes fumées du désert | M54: Les deux
A55: 8497 | B55: Survivre dans le désert | C55: Desert Survival Kits | D55: 60 | E55: 60 | G55: Demande des plats/composants | H55: Globe d'eau; Anti-venin puissant; Boulettes fumées du désert | M55: Alliance

Sheet QDB_Vendeurs
A1: Vend | B1: ID objet | C1: Objet (FR) | D1: Compétence requise | E1: ID PNJ | F1: PNJ (FR) | G1: Titre | H1: Zone | I1: Coordonnées | J1: Faction
A2: Composant | B2: 159 | C2: Eau de source | E2: 12196 | F2: Aubergiste Kaylisk | G2: Aubergiste | H2: Ashenvale | I2: 74.0, 60.6 | J2: Horde
A3: Composant | B3: 1179 | C3: Lait glacé | E3: 12196 | F3: Aubergiste Kaylisk | G3: Aubergiste | H3: Ashenvale | I3: 74.0, 60.6 | J3: Horde
A4: Composant | B4: 3713 | C4: Epices apaisantes | E4: 3954 | F4: Dalria | G4: Fournitures d'artisanat | H4: Ashenvale | I4: 35.1, 52.1 | J4: Alliance
A5: Composant | B5: 2678 | C5: Epices douces | E5: 3954 | F5: Dalria | G5: Fournitures d'artisanat | H5: Ashenvale | I5: 35.1, 52.1 | J5: Alliance
A6: Composant | B6: 2692 | C6: Epices fortes | E6: 3954 | F6: Dalria | G6: Fournitures d'artisanat | H6: Ashenvale | I6: 35.1, 52.1 | J6: Alliance
A7: Composant | B7: 4470 | C7: Bois simple | E7: 3962 | F7: Haljan Oakheart | G7: Fournitures générales | H7: Ashenvale | I7: 34.9, 50.9 | J7: Alliance
A8: Composant | B8: 159 | C8: Eau de source | E8: 3962 | F8: Haljan Oakheart | G8: Fournitures générales | H8: Ashenvale | I8: 34.9, 50.9 | J8: Alliance
A9: Composant | B9: 1179 | C9: Lait glacé | E9: 3962 | F9: Haljan Oakheart | G9: Fournitures générales | H9: Ashenvale | I9: 34.9, 50.9 | J9: Alliance
A10: Composant | B10: 159 | C10: Eau de source | E10: 6738 | F10: Kimlya l'aubergiste | G10: Aubergiste | H10: Ashenvale | I10: 37.0, 49.2 | J10: Alliance
A11: Composant | B11: 1179 | C11: Lait glacé | E11: 6738 | F11: Kimlya l'aubergiste | G11: Aubergiste | H11: Ashenvale | I11: 37.0, 49.2 | J11: Alliance
A12: Composant | B12: 159 | C12: Eau de source | E12: 3961 | F12: Maliynn | G12: Marchand de nourriture & boissons | H12: Ashenvale | I12: 36.6, 50.0 | J12: Alliance
A13: Composant | B13: 1179 | C13: Lait glacé | E13: 3961 | F13: Maliynn | G13: Marchand de nourriture & boissons | H13: Ashenvale | I13: 36.6, 50.0 | J13: Alliance
... A203: Composant | B203: 1179 | C203: Lait glacé | E203: 6739 | F203: Aubergiste Bates | G203: Aubergiste | H203: Forêt des Pins argentés | I203: 43.2, 41.3 | J203: Horde
A204: Composant | B204: 1179 | C204: Lait glacé | E204: 3577 | F204: Brasseur de Dalaran | H204: Forêt des Pins argentés | I204: 62.6, 65.0 | J204: Les deux
A205: Composant | B205: 4470 | C205: Bois simple | E205: 2140 | F205: Edwin Harly | G205: Fournitures générales | H205: Forêt des Pins argentés | I205: 44.0, 39.9 | J205: Horde
A206: Composant | B206: 159 | C206: Eau de source | E206: 2140 | F206: Edwin Harly | G206: Fournitures générales | H206: Forêt des Pins argentés | I206: 44.0, 39.9 | J206: Horde
A207: Composant | B207: 1179 | C207: Lait glacé | E207: 2140 | F207: Edwin Harly | G207: Fournitures générales | H207: Forêt des Pins argentés | I207: 44.0, 39.9 | J207: Horde
A208: Composant | B208: 4470 | C208: Bois simple | E208: 5758 | F208: Leo Sarn | G208: Fournitures d'enchanteur | H208: Forêt des Pins argentés | I208: 53.9, 82.2 | J208: Horde
A209: Composant | B209: 4470 | C209: Bois simple | E209: 5757 | F209: Lilly | G209: Fournitures d'enchanteur | H209: Forêt des Pins argentés | I209: 43.0, 50.8 | J209: Horde
A210: Composant | B210: 159 | C210: Eau de source | E210: 7737 | F210: Aubergiste Greul | G210: Aubergiste | H210: Féralas | I210: 74.8, 45.2 | J210: Horde
A211: Composant | B211: 1179 | C211: Lait glacé | E211: 7737 | F211: Aubergiste Greul | G211: Aubergiste | H211: Féralas | I211: 74.8, 45.2 | J211: Horde
A212: Composant | B212: 159 | C212: Eau de source | E212: 7736 | F212: Aubergiste Shyria | G212: Aubergiste | H212: Féralas | I212: 31.0, 43.5 | J212: Alliance
A213: Composant | B213: 1179 | C213: Lait glacé | E213: 7736 | F213: Aubergiste Shyria | G213: Aubergiste | H213: Féralas | I213: 31.0, 43.5 | J213: Alliance
A214: Composant | B214: 4536 | C214: Pomme rouge brillante | E214: 7736 | F214: Aubergiste Shyria | G214: Aubergiste | H214: Féralas | I214: 31.0, 43.5 | J214: Alliance
A215: Composant | B215: 4470 | C215: Bois simple | E215: 7942 | F215: Faralorn | G215: Fournitures générales | H215: Féralas | I215: 30.6, 43.4 | J215: Alliance
A216: Composant | B216: 159 | C216: Eau de source | E216: 7942 | F216: Faralorn | G216: Fournitures générales | H216: Féralas | I216: 30.6, 43.4 | J216: Alliance
... A232: Composant | B232: 1179 | C232: Lait glacé | E232: 2806 | F232: Bale | G232: Fournitures générales | H232: Gangrebois | I232: 34.8, 53.2 | J232: Horde
A233: Composant | B233: 4470 | C233: Bois simple | E233: 11555 | F233: Gorn le Borgne | H233: Gangrebois | I233: 65.2, 2.7 | J233: Hostile
A234: Composant | B234: 159 | C234: Eau de source | E234: 11555 | F234: Gorn le Borgne | H234: Gangrebois | I234: 65.2, 2.7 | J234: Hostile
A235: Composant | B235: 4470 | C235: Bois simple | E235: 2803 | F235: Malygen | G235: Fournitures générales | H235: Gangrebois | I235: 62.3, 25.6 | J235: Alliance
A236: Composant | B236: 159 | C236: Eau de source | E236: 2803 | F236: Malygen | G236: Fournitures générales | H236: Gangrebois | I236: 62.3, 25.6 | J236: Alliance
A237: Composant | B237: 1179 | C237: Lait glacé | E237: 2803 | F237: Malygen | G237: Fournitures générales | H237: Gangrebois | I237: 62.3, 25.6 | J237: Alliance
A238: Composant | B238: 4470 | C238: Bois simple | E238: 14624 | F238: Maître forgeron Burninate | G238: La Confrérie du thorium | H238: Gorge des Vents brûlants | I238: 38.8, 28.5 | J238: Les deux
A239: Composant | B239: 159 | C239: Eau de source | E239: 14624 | F239: Maître forgeron Burninate | G239: La Confrérie du thorium | H239: Gorge des Vents brûlants | I239: 38.8, 28.5 | J239: Les deux
A240: Composant | B240: 1179 | C240: Lait glacé | E240: 14624 | F240: Maître forgeron Burninate | G240: La Confrérie du thorium | H240: Gorge des Vents brûlants | I240: 38.8, 28.5 | J240: Les deux
A241: Composant | B241: 159 | C241: Eau de source | E241: 14371 | F241: Approvisionneur Shen'dralar | H241: Hache-tripes | I241: instance | J241: Les deux
A242: Composant | B242: 1179 | C242: Lait glacé | E242: 14371 | F242: Approvisionneur Shen'dralar | H242: Hache-tripes | I242: instance | J242: Les deux
A243: Composant | B243: 159 | C243: Eau de source | E243: 12794 | F243: Garde de pierre Zarg | G243: Nourriture et boissons | H243: Hall of Legends | I243: instance | J243: Horde
A244: Composant | B244: 1179 | C244: Lait glacé | E244: 12794 | F244: Garde de pierre Zarg | G244: Nourriture et boissons | H244: Hall of Legends | I244: instance | J244: Horde
A245: Composant | B245: 2596 | C245: Outre de bière naine | E245: 12794 | F245: Garde de pierre Zarg | G245: Nourriture et boissons | H245: Hall of Legends | I245: instance | J245: Horde
A246: Composant | B246: 4536 | C246: Pomme rouge brillante | E246: 12794 | F246: Garde de pierre Zarg | G246: Nourriture et boissons | H246: Hall of Legends | I246: instance | J246: Horde
A247: Composant | B247: 159 | C247: Eau de source | E247: 9501 | F247: Aubergiste Adegwa | G247: Aubergiste | H247: Hautes-terres d'Arathi | I247: 73.8, 32.5 | J247: Horde
A248: Composant | B248: 1179 | C248: Lait glacé | E248: 9501 | F248: Aubergiste Adegwa | G248: Aubergiste | H248: Hautes-terres d'Arathi | I248: 73.8, 32.5 | J248: Horde
A249: Composant | B249: 4470 | C249: Bois simple | E249: 2820 | F249: Graud | G249: Fournitures générales | H249: Hautes-terres d'Arathi | I249: 74.1, 32.4 | J249: Horde
A250: Composant | B250: 159 | C250: Eau de source | E250: 2820 | F250: Graud | G250: Fournitures générales | H250: Hautes-terres d'Arathi | I250: 74.1, 32.4 | J250: Horde
A251: Composant | B251: 3713 | C251: Epices apaisantes | E251: 2810 | F251: Hammon Karwn | G251: Excellent commerçant | H251: Hautes-terres d'Arathi | I251: 46.5, 47.4 | J251: Alliance
A252: Composant | B252: 2678 | C252: Epices douces | E252: 2810 | F252: Hammon Karwn | G252: Excellent commerçant | H252: Hautes-terres d'Arathi | I252: 46.5, 47.4 | J252: Alliance
A253: Composant | B253: 2692 | C253: Epices fortes | E253: 2810 | F253: Hammon Karwn | G253: Excellent commerçant | H253: Hautes-terres d'Arathi | I253: 46.5, 47.4 | J253: Alliance
A254: Composant | B254: 3713 | C254: Epices apaisantes | E254: 2821 | F254: Keena | G254: Fournitures d'artisanat | H254: Hautes-terres d'Arathi | I254: 74.1, 32.7 | J254: Horde
... A385: Composant | B385: 1179 | C385: Lait glacé | E385: 16256 | F385: Jessica Chambers | G385: Aubergiste | H385: Maleterres de l'est | I385: 71.8, 48.5 | J385: Les deux
A386: Composant | B386: 159 | C386: Eau de source | E386: 11287 | F386: Boulanger Masterson | H386: Maleterres de l'ouest | I386: 69.5, 79.7 | J386: Les deux
A387: Composant | B387: 1179 | C387: Lait glacé | E387: 11287 | F387: Boulanger Masterson | H387: Maleterres de l'ouest | I387: 69.5, 79.7 | J387: Les deux
A388: Composant | B388: 3713 | C388: Epices apaisantes | E388: 989 | F388: Banalash | G388: Fournitures d'artisanat | H388: Marais des Chagrins | I388: 44.8, 56.6 | J388: Horde
A389: Composant | B389: 2678 | C389: Epices douces | E389: 989 | F389: Banalash | G389: Fournitures d'artisanat | H389: Marais des Chagrins | I389: 44.8, 56.6 | J389: Horde
A390: Composant | B390: 2692 | C390: Epices fortes | E390: 989 | F390: Banalash | G390: Fournitures d'artisanat | H390: Marais des Chagrins | I390: 44.8, 56.6 | J390: Horde
A391: Composant | B391: 159 | C391: Eau de source | E391: 6930 | F391: Karakul l'aubergiste | G391: Aubergiste | H391: Marais des Chagrins | I391: 45.2, 56.7 | J391: Horde
A392: Composant | B392: 1179 | C392: Lait glacé | E392: 6930 | F392: Karakul l'aubergiste | G392: Aubergiste | H392: Marais des Chagrins | I392: 45.2, 56.7 | J392: Horde
A393: Composant | B393: 159 | C393: Eau de source | E393: 982 | F393: Thultash | G393: Marchand de nourriture & boissons | H393: Marais des Chagrins | I393: 46.5, 54.3 | J393: Horde
A394: Composant | B394: 1179 | C394: Lait glacé | E394: 982 | F394: Thultash | G394: Marchand de nourriture & boissons | H394: Marais des Chagrins | I394: 46.5, 54.3 | J394: Horde
A395: Composant | B395: 159 | C395: Eau de source | E395: 8931 | F395: Aubergiste Heather | G395: Aubergiste | H395: Marche de l'Ouest | I395: 52.9, 53.7 | J395: Alliance
A396: Composant | B396: 1179 | C396: Lait glacé | E396: 8931 | F396: Aubergiste Heather | G396: Aubergiste | H396: Marche de l'Ouest | I396: 52.9, 53.7 | J396: Alliance
A397: Composant | B397: 3713 | C397: Epices apaisantes | E397: 8934 | F397: Christopher Hewen | G397: Vendeur de fournitures générales | H397: Marche de l'Ouest | I397: 52.2, 52.8 | J397: Alliance
A398: Composant | B398: 2678 | C398: Epices douces | E398: 8934 | F398: Christopher Hewen | G398: Vendeur de fournitures générales | H398: Marche de l'Ouest | I398: 52.2, 52.8 | J398: Alliance
A399: Composant | B399: 2692 | C399: Epices fortes | E399: 8934 | F399: Christopher Hewen | G399: Vendeur de fournitures générales | H399: Marche de l'Ouest | I399: 52.2, 52.8 | J399: Alliance
... A448: Composant | B448: 4470 | C448: Bois simple | E448: 3346 | F448: Kithas | G448: Fournitures d'enchanteur | H448: Orgrimmar | I448: 53.9, 38.0 | J448: Horde
A449: Composant | B449: 159 | C449: Eau de source | E449: 5611 | F449: Morag le tavernier | H449: Orgrimmar | I449: 54.6, 67.7 | J449: Horde
A450: Composant | B450: 1179 | C450: Lait glacé | E450: 5611 | F450: Morag le tavernier | H450: Orgrimmar | I450: 54.6, 67.7 | J450: Horde
A451: Composant | B451: 2596 | C451: Outre de bière naine | E451: 5611 | F451: Morag le tavernier | H451: Orgrimmar | I451: 54.6, 67.7 | J451: Horde
A452: Composant | B452: 17196 | C452: Eau de vie spéciale | E452: 13420 | F452: Penney Copperpinch | G452: Gourmandises Fumebois | H452: Orgrimmar | I452: 53.2, 65.9 | J452: Les deux
A453: Composant | B453: 17194 | C453: Epices spéciales | E453: 13420 | F453: Penney Copperpinch | G453: Gourmandises Fumebois | H453: Orgrimmar | I453: 53.2, 65.9 | J453: Les deux
A454: Composant | B454: 4536 | C454: Pomme rouge brillante | E454: 3342 | F454: Shan'ti | G454: Marchand de fruits | H454: Orgrimmar | I454: 37.4, 52.3 | J454: Horde
A455: Composant | B455: 3713 | C455: Epices apaisantes | E455: 5817 | F455: Shimra | G455: Marchand de fournitures universelles | H455: Orgrimmar | I455: 47.9, 80.3 | J455: Horde
A456: Composant | B456: 2678 | C456: Epices douces | E456: 5817 | F456: Shimra | G456: Marchand de fournitures universelles | H456: Orgrimmar | I456: 47.9, 80.3 | J456: Horde
A457: Composant | B457: 2692 | C457: Epices fortes | E457: 5817 | F457: Shimra | G457: Marchand de fournitures universelles | H457: Orgrimmar | I457: 47.9, 80.3 | J457: Horde
A458: Composant | B458: 4470 | C458: Bois simple | E458: 3313 | F458: Trak'gen | G458: Fournitures générales | H458: Orgrimmar | I458: 48.1, 80.5 | J458: Horde
A459: Composant | B459: 159 | C459: Eau de source | E459: 3313 | F459: Trak'gen | G459: Fournitures générales | H459: Orgrimmar | I459: 48.1, 80.5 | J459: Horde
A460: Composant | B460: 1179 | C460: Lait glacé | E460: 3313 | F460: Trak'gen | G460: Fournitures générales | H460: Orgrimmar | I460: 48.1, 80.5 | J460: Horde
A461: Composant | B461: 159 | C461: Eau de source | E461: 3400 | F461: Xen'to | G461: Fournitures de cuisinier | H461: Orgrimmar | I461: 57.6, 52.9 | J461: Horde
A462: Composant | B462: 3713 | C462: Epices apaisantes | E462: 3400 | F462: Xen'to | G462: Fournitures de cuisinier | H462: Orgrimmar | I462: 57.6, 52.9 | J462: Horde
A463: Composant | B463: 2678 | C463: Epices douces | E463: 3400 | F463: Xen'to | G463: Fournitures de cuisinier | H463: Orgrimmar | I463: 57.6, 52.9 | J463: Horde
... A474: Composant | B474: 1179 | C474: Lait glacé | E474: 12026 | F474: My'lanna | G474: Marchand de nourriture & boissons | H474: Reflet-de-Lune | I474: 44.5, 33.9 | J474: Les deux
A475: Composant | B475: 4470 | C475: Bois simple | E475: 12246 | F475: Super-Vendeur 680 | H475: Royaumes de l'est | J475: Les deux
A476: Composant | B476: 159 | C476: Eau de source | E476: 12246 | F476: Super-Vendeur 680 | H476: Royaumes de l'est | J476: Les deux
A477: Composant | B477: 3713 | C477: Epices apaisantes | E477: 12245 | F477: Vendeur-Tron 1000 | H477: Royaumes de l'est | J477: Les deux
A478: Composant | B478: 2678 | C478: Epices douces | E478: 12245 | F478: Vendeur-Tron 1000 | H478: Royaumes de l'est | J478: Les deux
A479: Composant | B479: 2692 | C479: Epices fortes | E479: 12245 | F479: Vendeur-Tron 1000 | H479: Royaumes de l'est | J479: Les deux
A480: Composant | B480: 4470 | C480: Bois simple | E480: 15174 | F480: Calandrath | G480: Aubergiste | H480: Silithus | I480: 51.9, 39.2 | J480: Les deux
A481: Composant | B481: 159 | C481: Eau de source | E481: 15174 | F481: Calandrath | G481: Aubergiste | H481: Silithus | I481: 51.9, 39.2 | J481: Les deux
A482: Composant | B482: 1179 | C482: Lait glacé | E482: 15174 | F482: Calandrath | G482: Aubergiste | H482: Silithus | I482: 51.9, 39.2 | J482: Les deux
A483: Composant | B483: 4470 | C483: Bois simple | E483: 15419 | F483: Kania | G483: Fournitures d'enchanteur | H483: Silithus | I483: 52.0, 39.7 | J483: Les deux
A484: Composant | B484: 3713 | C484: Epices apaisantes | E484: 15179 | F484: Mishta | G484: Vendeur de fournitures générales | H484: Silithus | I484: 49.9, 36.3 | J484: Les deux
A485: Composant | B485: 2678 | C485: Epices douces | E485: 15179 | F485: Mishta | G485: Vendeur de fournitures générales | H485: Silithus | I485: 49.9, 36.3 | J485: Les deux
A486: Composant | B486: 2692 | C486: Epices fortes | E486: 15179 | F486: Mishta | G486: Vendeur de fournitures générales | H486: Silithus | I486: 49.9, 36.3 | J486: Les deux
A487: Composant | B487: 159 | C487: Eau de source | E487: 4191 | F487: Allyndia | G487: Marchand de nourriture & boissons | H487: Sombrivage | I487: 37.1, 43.6 | J487: Alliance
A488: Composant | B488: 1179 | C488: Lait glacé | E488: 4191 | F488: Allyndia | G488: Marchand de nourriture & boissons | H488: Sombrivage | I488: 37.1, 43.6 | J488: Alliance
A489: Composant | B489: 4536 | C489: Pomme rouge brillante | E489: 4191 | F489: Allyndia | G489: Marchand de nourriture & boissons | H489: Sombrivage | I489: 37.1, 43.6 | J489: Alliance
A490: Composant | B490: 4470 | C490: Bois simple | E490: 4182 | F490: Dalmond | G490: Fournitures générales | H490: Sombrivage | I490: 37.5, 40.5 | J490: Alliance
A491: Composant | B491: 159 | C491: Eau de source | E491: 4182 | F491: Dalmond | G491: Fournitures générales | H491: Sombrivage | I491: 37.5, 40.5 | J491: Alliance
... A615: Composant | B615: 159 | C615: Eau de source | E615: 1149 | F615: Uthok | G615: Fournitures générales | H615: Vallée de Strangleronce | I615: 31.6, 27.9 | J615: Horde
...
